{"type": "block", "layer": 0, "block": 521, "features": [{"geom": {"polygons": [[[[-0.050180013930869904, -0.057296377966780554], [-0.050118413930860584, -0.05734407796678198], [-0.05015951393086482, -0.0573932779667814], [-0.0502212139308682, -0.05734557796678175], [-0.050180013930869904, -0.057296377966780554]]]], "centroids": [[-0.05016979721291648, -0.057344828209224374, 0.0]], "h": 6.474861360399046e-06}, "mtl": {"idx": 0}, "prop": ["72847", "building.72847", "NULL", "NULL", "NULL", "NULL", "NULL", "NULL", "-1", "0", "-1", "NULL", "NULL", "w657096844", "657096844", "way", "yes", "NULL", "NULL", "NULL", "NULL", "NULL", "NULL", "NULL", "NULL", "NULL", "NULL", "NULL", "NULL", "NULL", "NULL", "NULL", "NULL", "NULL", "NULL", "NULL", "NULL", "NULL", "NULL", "NULL", "NULL", "NULL", "NULL", "NULL", "NULL", "NULL", "NULL", "NULL", "NULL", "NULL", "NULL", "NULL", "NULL", "NULL", "NULL", "NULL", "NULL", "NULL", "NULL", "NULL", "NULL", "NULL", "NULL", "NULL", "NULL", "NULL", "NULL", "NULL", "NULL", "NULL", "NULL", "NULL", "NULL", "NULL", "NULL", "NULL", "NULL", "NULL", "NULL", "NULL", "NULL", "NULL", "NULL", "NULL", "NULL", "NULL", "NULL", "NULL", "NULL", "NULL", "NULL", "NULL", "NULL", "NULL", "NULL", "NULL", "NULL", "NULL", "NULL", "NULL", "NULL", "NULL", "NULL", "NULL", "NULL", "NULL", "NULL", "NULL", "NULL", "NULL", "NULL", "NULL", "NULL", "NULL", "NULL", "NULL", "NULL", "NULL", "NULL", "NULL", "NULL", "NULL", "NULL", "NULL", "NULL", "NULL", "NULL", "NULL", "NULL", "NULL", "NULL", "NULL", "NULL", "NULL", "NULL", "NULL", "NULL", "NULL", "NULL", "NULL", "NULL", "NULL", "NULL", "NULL", "NULL", "NULL", "NULL", "NULL", "NULL", "NULL", "NULL", "NULL", "NULL", "NULL", "NULL", "NULL", "NULL", "NULL", "NULL", "NULL", "NULL", "NULL", "NULL", "NULL", "NULL", "NULL", "NULL", "NULL", "NULL", "NULL", "NULL", "NULL", "NULL", "NULL", "NULL", "NULL", "NULL", "NULL", "NULL", "NULL", "NULL", "NULL", "NULL", "NULL", "NULL", "NULL", "0.06474861360399045", "0.6176729238862184", "9.539554432222642"]}, {"geom": {"polygons": [[[[-0.05020281393086634, -0.05721257796678181], [-0.050179213930860556, -0.05718057796678089], [-0.050139613930866744, -0.05720767796678139], [-0.05016331393086659, -0.05723967796678053], [-0.05020281393086634, -0.05721257796678181]]]], "centroids": [[-0.050171230938062195, -0.05721012670098702, 0.0]], "h": 2.47084343931867e-06}, "mtl": {"idx": 0}, "prop": ["72849", "building.72849", "NULL", "NULL", "NULL", "NULL", "NULL", "NULL", "-1", "0", "-1", "NULL", "NULL", "w657096846", "657096846", "way", "yes", "NULL", "NULL", "NULL", "NULL", "NULL", "NULL", "NULL", "NULL", "NULL", "NULL", "NULL", "NULL", "NULL", "NULL", "NULL", "NULL", "NULL", "NULL", "NULL", "NULL", "NULL", "NULL", "NULL", "NULL", "NULL", "NULL", "NULL", "NULL", "NULL", "NULL", "NULL", "NULL", "NULL", "NULL", "NULL", "NULL", "NULL", "NULL", "NULL", "NULL", "NULL", "NULL", "NULL", "NULL", "NULL", "NULL", "NULL", "NULL", "NULL", "NULL", "NULL", "NULL", "NULL", "NULL", "NULL", "NULL", "NULL", "NULL", "NULL", "NULL", "NULL", "NULL", "NULL", "NULL", "NULL", "NULL", "NULL", "NULL", "NULL", "NULL", "NULL", "NULL", "NULL", "NULL", "NULL", "NULL", "NULL", "NULL", "NULL", "NULL", "NULL", "NULL", "NULL", "NULL", "NULL", "NULL", "NULL", "NULL", "NULL", "NULL", "NULL", "NULL", "NULL", "NULL", "NULL", "NULL", "NULL", "NULL", "NULL", "NULL", "NULL", "NULL", "NULL", "NULL", "NULL", "NULL", "NULL", "NULL", "NULL", "NULL", "NULL", "NULL", "NULL", "NULL", "NULL", "NULL", "NULL", "NULL", "NULL", "NULL", "NULL", "NULL", "NULL", "NULL", "NULL", "NULL", "NULL", "NULL", "NULL", "NULL", "NULL", "NULL", "NULL", "NULL", "NULL", "NULL", "NULL", "NULL", "NULL", "NULL", "NULL", "NULL", "NULL", "NULL", "NULL", "NULL", "NULL", "NULL", "NULL", "NULL", "NULL", "NULL", "NULL", "NULL", "NULL", "NULL", "NULL", "NULL", "NULL", "NULL", "NULL", "NULL", "NULL", "NULL", "NULL", "NULL", "NULL", "NULL", "NULL", "0.0247084343931867", "0.2223759095386803", "9"]}, {"geom": {"polygons": [[[[-0.05018271393086593, -0.05670467796678125], [-0.05015581393087132, -0.05667587796678042], [-0.050115613930870495, -0.05671067796678031], [-0.05014251393086511, -0.05673947796678114], [-0.05018271393086593, -0.05670467796678125]]]], "centroids": [[-0.05014916393086821, -0.056707677966782555, 0.0]], "h": 2.7136684799248758e-06}, "mtl": {"idx": 0}, "prop": ["72844", "building.72844", "NULL", "NULL", "NULL", "NULL", "NULL", "NULL", "-1", "0", "-1", "NULL", "NULL", "w657096840", "657096840", "way", "yes", "NULL", "NULL", "NULL", "NULL", "NULL", "NULL", "NULL", "NULL", "NULL", "NULL", "NULL", "NULL", "NULL", "NULL", "NULL", "NULL", "NULL", "NULL", "NULL", "NULL", "NULL", "NULL", "NULL", "NULL", "NULL", "NULL", "NULL", "NULL", "NULL", "NULL", "NULL", "NULL", "NULL", "NULL", "NULL", "NULL", "NULL", "NULL", "NULL", "NULL", "NULL", "NULL", "NULL", "NULL", "NULL", "NULL", "NULL", "NULL", "NULL", "NULL", "NULL", "NULL", "NULL", "NULL", "NULL", "NULL", "NULL", "NULL", "NULL", "NULL", "NULL", "NULL", "NULL", "NULL", "NULL", "NULL", "NULL", "NULL", "NULL", "NULL", "NULL", "NULL", "NULL", "NULL", "NULL", "NULL", "NULL", "NULL", "NULL", "NULL", "NULL", "NULL", "NULL", "NULL", "NULL", "NULL", "NULL", "NULL", "NULL", "NULL", "NULL", "NULL", "NULL", "NULL", "NULL", "NULL", "NULL", "NULL", "NULL", "NULL", "NULL", "NULL", "NULL", "NULL", "NULL", "NULL", "NULL", "NULL", "NULL", "NULL", "NULL", "NULL", "NULL", "NULL", "NULL", "NULL", "NULL", "NULL", "NULL", "NULL", "NULL", "NULL", "NULL", "NULL", "NULL", "NULL", "NULL", "NULL", "NULL", "NULL", "NULL", "NULL", "NULL", "NULL", "NULL", "NULL", "NULL", "NULL", "NULL", "NULL", "NULL", "NULL", "NULL", "NULL", "NULL", "NULL", "NULL", "NULL", "NULL", "NULL", "NULL", "NULL", "NULL", "NULL", "NULL", "NULL", "NULL", "NULL", "NULL", "NULL", "NULL", "NULL", "NULL", "NULL", "NULL", "NULL", "NULL", "NULL", "NULL", "0.027136684799248755", "0.27136684799248756", "10"]}, {"geom": {"polygons": [[[[-0.05016831393086818, -0.057271777966780846], [-0.050108513930865684, -0.057203977966780784], [-0.050060813930869585, -0.057242877966780625], [-0.0500877139308642, -0.05727327796678061], [-0.050020713930862826, -0.05732787796678096], [-0.05005361393087071, -0.057365277966781036], [-0.05016831393086818, -0.057271777966780846]]]], "centroids": [[-0.050095413988827886, -0.057284351120214794, 0.0]], "h": 1.2776654881262052e-05}, "mtl": {"idx": 0}, "prop": ["35803", "building.35803", "NULL", "NULL", "NULL", "NULL", "NULL", "NULL", "-1", "0", "-1", "NULL", "NULL", "w603132564", "603132564", "way", "yes", "NULL", "NULL", "NULL", "NULL", "NULL", "NULL", "NULL", "NULL", "NULL", "NULL", "NULL", "NULL", "NULL", "NULL", "NULL", "NULL", "NULL", "NULL", "NULL", "NULL", "NULL", "NULL", "NULL", "NULL", "NULL", "NULL", "NULL", "NULL", "NULL", "NULL", "NULL", "NULL", "NULL", "NULL", "NULL", "NULL", "NULL", "NULL", "NULL", "NULL", "NULL", "NULL", "NULL", "NULL", "NULL", "NULL", "NULL", "NULL", "NULL", "NULL", "NULL", "NULL", "NULL", "NULL", "NULL", "NULL", "NULL", "NULL", "NULL", "NULL", "NULL", "NULL", "NULL", "NULL", "NULL", "NULL", "NULL", "NULL", "NULL", "NULL", "NULL", "NULL", "NULL", "NULL", "NULL", "NULL", "NULL", "NULL", "NULL", "NULL", "NULL", "NULL", "NULL", "NULL", "NULL", "NULL", "NULL", "NULL", "NULL", "NULL", "NULL", "NULL", "NULL", "NULL", "NULL", "NULL", "NULL", "NULL", "NULL", "NULL", "NULL", "NULL", "NULL", "NULL", "NULL", "NULL", "NULL", "NULL", "NULL", "NULL", "NULL", "NULL", "NULL", "NULL", "NULL", "NULL", "NULL", "NULL", "NULL", "NULL", "NULL", "NULL", "NULL", "NULL", "NULL", "NULL", "NULL", "NULL", "NULL", "NULL", "NULL", "NULL", "NULL", "NULL", "NULL", "NULL", "NULL", "NULL", "NULL", "NULL", "NULL", "NULL", "NULL", "NULL", "NULL", "NULL", "NULL", "NULL", "NULL", "NULL", "NULL", "NULL", "NULL", "NULL", "NULL", "NULL", "NULL", "NULL", "NULL", "NULL", "NULL", "NULL", "NULL", "NULL", "NULL", "NULL", "NULL", "NULL", "NULL", "0.1277665488126205", "1.1567545514435997", "9.053657332014732"]}, {"geom": {"polygons": [[[[-0.05014651393086922, -0.05666987796678136], [-0.050106313930868396, -0.056629177966781796], [-0.05006611393086757, -0.0566658779667808], [-0.050106313930868396, -0.05670657796678036], [-0.05014651393086922, -0.05666987796678136]]]], "centroids": [[-0.050106313930868396, -0.056667877966782854, 0.0]], "h": 4.032478080106708e-06}, "mtl": {"idx": 0}, "prop": ["72843", "building.72843", "NULL", "NULL", "NULL", "NULL", "NULL", "NULL", "-1", "0", "-1", "NULL", "NULL", "w657096839", "657096839", "way", "yes", "NULL", "NULL", "NULL", "NULL", "NULL", "NULL", "NULL", "NULL", "NULL", "NULL", "NULL", "NULL", "NULL", "NULL", "NULL", "NULL", "NULL", "NULL", "NULL", "NULL", "NULL", "NULL", "NULL", "NULL", "NULL", "NULL", "NULL", "NULL", "NULL", "NULL", "NULL", "NULL", "NULL", "NULL", "NULL", "NULL", "NULL", "NULL", "NULL", "NULL", "NULL", "NULL", "NULL", "NULL", "NULL", "NULL", "NULL", "NULL", "NULL", "NULL", "NULL", "NULL", "NULL", "NULL", "NULL", "NULL", "NULL", "NULL", "NULL", "NULL", "NULL", "NULL", "NULL", "NULL", "NULL", "NULL", "NULL", "NULL", "NULL", "NULL", "NULL", "NULL", "NULL", "NULL", "NULL", "NULL", "NULL", "NULL", "NULL", "NULL", "NULL", "NULL", "NULL", "NULL", "NULL", "NULL", "NULL", "NULL", "NULL", "NULL", "NULL", "NULL", "NULL", "NULL", "NULL", "NULL", "NULL", "NULL", "NULL", "NULL", "NULL", "NULL", "NULL", "NULL", "NULL", "NULL", "NULL", "NULL", "NULL", "NULL", "NULL", "NULL", "NULL", "NULL", "NULL", "NULL", "NULL", "NULL", "NULL", "NULL", "NULL", "NULL", "NULL", "NULL", "NULL", "NULL", "NULL", "NULL", "NULL", "NULL", "NULL", "NULL", "NULL", "NULL", "NULL", "NULL", "NULL", "NULL", "NULL", "NULL", "NULL", "NULL", "NULL", "NULL", "NULL", "NULL", "NULL", "NULL", "NULL", "NULL", "NULL", "NULL", "NULL", "NULL", "NULL", "NULL", "NULL", "NULL", "NULL", "NULL", "NULL", "NULL", "NULL", "NULL", "NULL", "NULL", "NULL", "NULL", "NULL", "0.040324780801067085", "0.40324780801067084", "10"]}, {"geom": {"polygons": [[[[-0.05008351393087196, -0.05720487796678064], [-0.05004971393086066, -0.057164677966781596], [-0.05000411393086779, -0.05720007796678139], [-0.050037913930864875, -0.05724027796678044], [-0.05008351393087196, -0.05720487796678064]]]], "centroids": [[-0.050043813930884085, -0.05720247796678102, 0.0]], "h": 3.926413439754921e-06}, "mtl": {"idx": 0}, "prop": ["72850", "building.72850", "NULL", "NULL", "NULL", "NULL", "NULL", "NULL", "-1", "0", "-1", "NULL", "NULL", "w657096847", "657096847", "way", "yes", "NULL", "NULL", "NULL", "NULL", "NULL", "NULL", "NULL", "NULL", "NULL", "NULL", "NULL", "NULL", "NULL", "NULL", "NULL", "NULL", "NULL", "NULL", "NULL", "NULL", "NULL", "NULL", "NULL", "NULL", "NULL", "NULL", "NULL", "NULL", "NULL", "NULL", "NULL", "NULL", "NULL", "NULL", "NULL", "NULL", "NULL", "NULL", "NULL", "NULL", "NULL", "NULL", "NULL", "NULL", "NULL", "NULL", "NULL", "NULL", "NULL", "NULL", "NULL", "NULL", "NULL", "NULL", "NULL", "NULL", "NULL", "NULL", "NULL", "NULL", "NULL", "NULL", "NULL", "NULL", "NULL", "NULL", "NULL", "NULL", "NULL", "NULL", "NULL", "NULL", "NULL", "NULL", "NULL", "NULL", "NULL", "NULL", "NULL", "NULL", "NULL", "NULL", "NULL", "NULL", "NULL", "NULL", "NULL", "NULL", "NULL", "NULL", "NULL", "NULL", "NULL", "NULL", "NULL", "NULL", "NULL", "NULL", "NULL", "NULL", "NULL", "NULL", "NULL", "NULL", "NULL", "NULL", "NULL", "NULL", "NULL", "NULL", "NULL", "NULL", "NULL", "NULL", "NULL", "NULL", "NULL", "NULL", "NULL", "NULL", "NULL", "NULL", "NULL", "NULL", "NULL", "NULL", "NULL", "NULL", "NULL", "NULL", "NULL", "NULL", "NULL", "NULL", "NULL", "NULL", "NULL", "NULL", "NULL", "NULL", "NULL", "NULL", "NULL", "NULL", "NULL", "NULL", "NULL", "NULL", "NULL", "NULL", "NULL", "NULL", "NULL", "NULL", "NULL", "NULL", "NULL", "NULL", "NULL", "NULL", "NULL", "NULL", "NULL", "NULL", "NULL", "NULL", "NULL", "NULL", "NULL", "0.03926413439754921", "0.3533772095779429", "9"]}, {"geom": {"polygons": [[[[-0.05008951393087102, -0.05662147796678063], [-0.0500555139308716, -0.056582177966781444], [-0.05000791393086956, -0.056620177966781426], [-0.050041913930868986, -0.05665957796678178], [-0.05008951393087102, -0.05662147796678063]]]], "centroids": [[-0.050048711010546754, -0.05662086125358812, 0.0]], "h": 4.1041209603599865e-06}, "mtl": {"idx": 0}, "prop": ["72842", "building.72842", "NULL", "NULL", "NULL", "NULL", "NULL", "NULL", "-1", "0", "-1", "NULL", "NULL", "w657096838", "657096838", "way", "yes", "NULL", "NULL", "NULL", "NULL", "NULL", "NULL", "NULL", "NULL", "NULL", "NULL", "NULL", "NULL", "NULL", "NULL", "NULL", "NULL", "NULL", "NULL", "NULL", "NULL", "NULL", "NULL", "NULL", "NULL", "NULL", "NULL", "NULL", "NULL", "NULL", "NULL", "NULL", "NULL", "NULL", "NULL", "NULL", "NULL", "NULL", "NULL", "NULL", "NULL", "NULL", "NULL", "NULL", "NULL", "NULL", "NULL", "NULL", "NULL", "NULL", "NULL", "NULL", "NULL", "NULL", "NULL", "NULL", "NULL", "NULL", "NULL", "NULL", "NULL", "NULL", "NULL", "NULL", "NULL", "NULL", "NULL", "NULL", "NULL", "NULL", "NULL", "NULL", "NULL", "NULL", "NULL", "NULL", "NULL", "NULL", "NULL", "NULL", "NULL", "NULL", "NULL", "NULL", "NULL", "NULL", "NULL", "NULL", "NULL", "NULL", "NULL", "NULL", "NULL", "NULL", "NULL", "NULL", "NULL", "NULL", "NULL", "NULL", "NULL", "NULL", "NULL", "NULL", "NULL", "NULL", "NULL", "NULL", "NULL", "NULL", "NULL", "NULL", "NULL", "NULL", "NULL", "NULL", "NULL", "NULL", "NULL", "NULL", "NULL", "NULL", "NULL", "NULL", "NULL", "NULL", "NULL", "NULL", "NULL", "NULL", "NULL", "NULL", "NULL", "NULL", "NULL", "NULL", "NULL", "NULL", "NULL", "NULL", "NULL", "NULL", "NULL", "NULL", "NULL", "NULL", "NULL", "NULL", "NULL", "NULL", "NULL", "NULL", "NULL", "NULL", "NULL", "NULL", "NULL", "NULL", "NULL", "NULL", "NULL", "NULL", "NULL", "NULL", "NULL", "NULL", "NULL", "NULL", "NULL", "NULL", "0.04104120960359987", "0.41041209603599865", "10"]}, {"geom": {"polygons": [[[[-0.050001713930868164, -0.05661507796678045], [-0.04995531393086594, -0.05656807796678187], [-0.04992851393086539, -0.05659257796678041], [-0.049974913930867615, -0.05663957796678076], [-0.050001713930868164, -0.05661507796678045]]]], "centroids": [[-0.04996511393088099, -0.056603827966782205, 0.0]], "h": 3.1057343998419657e-06}, "mtl": {"idx": 0}, "prop": ["72841", "building.72841", "NULL", "NULL", "NULL", "NULL", "NULL", "NULL", "-1", "0", "-1", "NULL", "NULL", "w657096837", "657096837", "way", "yes", "NULL", "NULL", "NULL", "NULL", "NULL", "NULL", "NULL", "NULL", "NULL", "NULL", "NULL", "NULL", "NULL", "NULL", "NULL", "NULL", "NULL", "NULL", "NULL", "NULL", "NULL", "NULL", "NULL", "NULL", "NULL", "NULL", "NULL", "NULL", "NULL", "NULL", "NULL", "NULL", "NULL", "NULL", "NULL", "NULL", "NULL", "NULL", "NULL", "NULL", "NULL", "NULL", "NULL", "NULL", "NULL", "NULL", "NULL", "NULL", "NULL", "NULL", "NULL", "NULL", "NULL", "NULL", "NULL", "NULL", "NULL", "NULL", "NULL", "NULL", "NULL", "NULL", "NULL", "NULL", "NULL", "NULL", "NULL", "NULL", "NULL", "NULL", "NULL", "NULL", "NULL", "NULL", "NULL", "NULL", "NULL", "NULL", "NULL", "NULL", "NULL", "NULL", "NULL", "NULL", "NULL", "NULL", "NULL", "NULL", "NULL", "NULL", "NULL", "NULL", "NULL", "NULL", "NULL", "NULL", "NULL", "NULL", "NULL", "NULL", "NULL", "NULL", "NULL", "NULL", "NULL", "NULL", "NULL", "NULL", "NULL", "NULL", "NULL", "NULL", "NULL", "NULL", "NULL", "NULL", "NULL", "NULL", "NULL", "NULL", "NULL", "NULL", "NULL", "NULL", "NULL", "NULL", "NULL", "NULL", "NULL", "NULL", "NULL", "NULL", "NULL", "NULL", "NULL", "NULL", "NULL", "NULL", "NULL", "NULL", "NULL", "NULL", "NULL", "NULL", "NULL", "NULL", "NULL", "NULL", "NULL", "NULL", "NULL", "NULL", "NULL", "NULL", "NULL", "NULL", "NULL", "NULL", "NULL", "NULL", "NULL", "NULL", "NULL", "NULL", "NULL", "NULL", "NULL", "NULL", "NULL", "0.031057343998419657", "0.2967106882582793", "9.5536401397807"]}, {"geom": {"polygons": [[[[-0.04999561393086083, -0.056675677966781635], [-0.04997881393086345, -0.05665017796678029], [-0.049939913930870716, -0.0566740779667807], [-0.049956813930862154, -0.056699477966780876], [-0.04999561393086083, -0.056675677966781635]]]], "centroids": [[-0.049967788151789705, -0.05667484437169357, 0.0]], "h": 1.8022240789723095e-06}, "mtl": {"idx": 0}, "prop": ["72840", "building.72840", "NULL", "NULL", "NULL", "NULL", "NULL", "NULL", "-1", "0", "-1", "NULL", "NULL", "w657096836", "657096836", "way", "yes", "NULL", "NULL", "NULL", "NULL", "NULL", "NULL", "NULL", "NULL", "NULL", "NULL", "NULL", "NULL", "NULL", "NULL", "NULL", "NULL", "NULL", "NULL", "NULL", "NULL", "NULL", "NULL", "NULL", "NULL", "NULL", "NULL", "NULL", "NULL", "NULL", "NULL", "NULL", "NULL", "NULL", "NULL", "NULL", "NULL", "NULL", "NULL", "NULL", "NULL", "NULL", "NULL", "NULL", "NULL", "NULL", "NULL", "NULL", "NULL", "NULL", "NULL", "NULL", "NULL", "NULL", "NULL", "NULL", "NULL", "NULL", "NULL", "NULL", "NULL", "NULL", "NULL", "NULL", "NULL", "NULL", "NULL", "NULL", "NULL", "NULL", "NULL", "NULL", "NULL", "NULL", "NULL", "NULL", "NULL", "NULL", "NULL", "NULL", "NULL", "NULL", "NULL", "NULL", "NULL", "NULL", "NULL", "NULL", "NULL", "NULL", "NULL", "NULL", "NULL", "NULL", "NULL", "NULL", "NULL", "NULL", "NULL", "NULL", "NULL", "NULL", "NULL", "NULL", "NULL", "NULL", "NULL", "NULL", "NULL", "NULL", "NULL", "NULL", "NULL", "NULL", "NULL", "NULL", "NULL", "NULL", "NULL", "NULL", "NULL", "NULL", "NULL", "NULL", "NULL", "NULL", "NULL", "NULL", "NULL", "NULL", "NULL", "NULL", "NULL", "NULL", "NULL", "NULL", "NULL", "NULL", "NULL", "NULL", "NULL", "NULL", "NULL", "NULL", "NULL", "NULL", "NULL", "NULL", "NULL", "NULL", "NULL", "NULL", "NULL", "NULL", "NULL", "NULL", "NULL", "NULL", "NULL", "NULL", "NULL", "NULL", "NULL", "NULL", "NULL", "NULL", "NULL", "NULL", "NULL", "NULL", "0.018022240789723094", "0.17360858585438665", "9.633018883721956"]}, {"geom": {"polygons": [[[[-0.05080901393085924, -0.05717067796678066], [-0.050766413930873, -0.05713907796678086], [-0.05072341393086788, -0.05719257796678079], [-0.05076611393086239, -0.05722417796678059], [-0.05080901393085924, -0.05717067796678066]]]], "centroids": [[-0.0507662305824681, -0.05718163223464856, 0.0]], "h": 4.716137518698386e-06}, "mtl": {"idx": 0}, "prop": ["72875", "building.72875", "NULL", "NULL", "NULL", "NULL", "NULL", "NULL", "-1", "0", "-1", "NULL", "NULL", "w657096872", "657096872", "way", "yes", "NULL", "NULL", "NULL", "NULL", "NULL", "NULL", "NULL", "NULL", "NULL", "NULL", "NULL", "NULL", "NULL", "NULL", "NULL", "NULL", "NULL", "NULL", "NULL", "NULL", "NULL", "NULL", "NULL", "NULL", "NULL", "NULL", "NULL", "NULL", "NULL", "NULL", "NULL", "NULL", "NULL", "NULL", "NULL", "NULL", "NULL", "NULL", "NULL", "NULL", "NULL", "NULL", "NULL", "NULL", "NULL", "NULL", "NULL", "NULL", "NULL", "NULL", "NULL", "NULL", "NULL", "NULL", "NULL", "NULL", "NULL", "NULL", "NULL", "NULL", "NULL", "NULL", "NULL", "NULL", "NULL", "NULL", "NULL", "NULL", "NULL", "NULL", "NULL", "NULL", "NULL", "NULL", "NULL", "NULL", "NULL", "NULL", "NULL", "NULL", "NULL", "NULL", "NULL", "NULL", "NULL", "NULL", "NULL", "NULL", "NULL", "NULL", "NULL", "NULL", "NULL", "NULL", "NULL", "NULL", "NULL", "NULL", "NULL", "NULL", "NULL", "NULL", "NULL", "NULL", "NULL", "NULL", "NULL", "NULL", "NULL", "NULL", "NULL", "NULL", "NULL", "NULL", "NULL", "NULL", "NULL", "NULL", "NULL", "NULL", "NULL", "NULL", "NULL", "NULL", "NULL", "NULL", "NULL", "NULL", "NULL", "NULL", "NULL", "NULL", "NULL", "NULL", "NULL", "NULL", "NULL", "NULL", "NULL", "NULL", "NULL", "NULL", "NULL", "NULL", "NULL", "NULL", "NULL", "NULL", "NULL", "NULL", "NULL", "NULL", "NULL", "NULL", "NULL", "NULL", "NULL", "NULL", "NULL", "NULL", "NULL", "NULL", "NULL", "NULL", "NULL", "NULL", "NULL", "NULL", "NULL", "0.04716137518698386", "0.47161375186983856", "10"]}, {"geom": {"polygons": [[[[-0.05061051393086302, -0.0571494779667816], [-0.05054991393086539, -0.05718197796678126], [-0.0505855139308693, -0.05724317796678058], [-0.05064611393086693, -0.05721067796678092], [-0.05061051393086302, -0.0571494779667816]]]], "centroids": [[-0.05059801393086616, -0.05719632796678198, 0.0]], "h": 6.305973120115638e-06}, "mtl": {"idx": 0}, "prop": ["72876", "building.72876", "NULL", "NULL", "NULL", "NULL", "NULL", "NULL", "-1", "0", "-1", "NULL", "NULL", "w657096873", "657096873", "way", "yes", "NULL", "NULL", "NULL", "NULL", "NULL", "NULL", "NULL", "NULL", "NULL", "NULL", "NULL", "NULL", "NULL", "NULL", "NULL", "NULL", "NULL", "NULL", "NULL", "NULL", "NULL", "NULL", "NULL", "NULL", "NULL", "NULL", "NULL", "NULL", "NULL", "NULL", "NULL", "NULL", "NULL", "NULL", "NULL", "NULL", "NULL", "NULL", "NULL", "NULL", "NULL", "NULL", "NULL", "NULL", "NULL", "NULL", "NULL", "NULL", "NULL", "NULL", "NULL", "NULL", "NULL", "NULL", "NULL", "NULL", "NULL", "NULL", "NULL", "NULL", "NULL", "NULL", "NULL", "NULL", "NULL", "NULL", "NULL", "NULL", "NULL", "NULL", "NULL", "NULL", "NULL", "NULL", "NULL", "NULL", "NULL", "NULL", "NULL", "NULL", "NULL", "NULL", "NULL", "NULL", "NULL", "NULL", "NULL", "NULL", "NULL", "NULL", "NULL", "NULL", "NULL", "NULL", "NULL", "NULL", "NULL", "NULL", "NULL", "NULL", "NULL", "NULL", "NULL", "NULL", "NULL", "NULL", "NULL", "NULL", "NULL", "NULL", "NULL", "NULL", "NULL", "NULL", "NULL", "NULL", "NULL", "NULL", "NULL", "NULL", "NULL", "NULL", "NULL", "NULL", "NULL", "NULL", "NULL", "NULL", "NULL", "NULL", "NULL", "NULL", "NULL", "NULL", "NULL", "NULL", "NULL", "NULL", "NULL", "NULL", "NULL", "NULL", "NULL", "NULL", "NULL", "NULL", "NULL", "NULL", "NULL", "NULL", "NULL", "NULL", "NULL", "NULL", "NULL", "NULL", "NULL", "NULL", "NULL", "NULL", "NULL", "NULL", "NULL", "NULL", "NULL", "NULL", "NULL", "NULL", "NULL", "0.06305973120115638", "0.6305973120115638", "10"]}, {"geom": {"polygons": [[[[-0.0505167139308611, -0.05711917796678101], [-0.05048351393087103, -0.05710607796678069], [-0.05045401393086024, -0.05717497796678117], [-0.05048721393086453, -0.05718807796678149], [-0.0505167139308611, -0.05711917796678101]]]], "centroids": [[-0.05048536393086067, -0.057147077966783755, 0.0]], "h": 3.465413280279102e-06}, "mtl": {"idx": 0}, "prop": ["72877", "building.72877", "NULL", "NULL", "NULL", "NULL", "NULL", "NULL", "-1", "0", "-1", "NULL", "NULL", "w657096874", "657096874", "way", "yes", "NULL", "NULL", "NULL", "NULL", "NULL", "NULL", "NULL", "NULL", "NULL", "NULL", "NULL", "NULL", "NULL", "NULL", "NULL", "NULL", "NULL", "NULL", "NULL", "NULL", "NULL", "NULL", "NULL", "NULL", "NULL", "NULL", "NULL", "NULL", "NULL", "NULL", "NULL", "NULL", "NULL", "NULL", "NULL", "NULL", "NULL", "NULL", "NULL", "NULL", "NULL", "NULL", "NULL", "NULL", "NULL", "NULL", "NULL", "NULL", "NULL", "NULL", "NULL", "NULL", "NULL", "NULL", "NULL", "NULL", "NULL", "NULL", "NULL", "NULL", "NULL", "NULL", "NULL", "NULL", "NULL", "NULL", "NULL", "NULL", "NULL", "NULL", "NULL", "NULL", "NULL", "NULL", "NULL", "NULL", "NULL", "NULL", "NULL", "NULL", "NULL", "NULL", "NULL", "NULL", "NULL", "NULL", "NULL", "NULL", "NULL", "NULL", "NULL", "NULL", "NULL", "NULL", "NULL", "NULL", "NULL", "NULL", "NULL", "NULL", "NULL", "NULL", "NULL", "NULL", "NULL", "NULL", "NULL", "NULL", "NULL", "NULL", "NULL", "NULL", "NULL", "NULL", "NULL", "NULL", "NULL", "NULL", "NULL", "NULL", "NULL", "NULL", "NULL", "NULL", "NULL", "NULL", "NULL", "NULL", "NULL", "NULL", "NULL", "NULL", "NULL", "NULL", "NULL", "NULL", "NULL", "NULL", "NULL", "NULL", "NULL", "NULL", "NULL", "NULL", "NULL", "NULL", "NULL", "NULL", "NULL", "NULL", "NULL", "NULL", "NULL", "NULL", "NULL", "NULL", "NULL", "NULL", "NULL", "NULL", "NULL", "NULL", "NULL", "NULL", "NULL", "NULL", "NULL", "NULL", "NULL", "0.03465413280279102", "0.31188719522511915", "9"]}, {"geom": {"polygons": [[[[-0.05067831393085953, -0.05705147796678034], [-0.05064891393087123, -0.05701167796678064], [-0.050597913930872096, -0.05704647796678053], [-0.050627313930860396, -0.057086277966782006], [-0.05067831393085953, -0.05705147796678034]]]], "centroids": [[-0.050638113930830286, -0.05704897796677777, 0.0]], "h": 3.9565843196118745e-06}, "mtl": {"idx": 0}, "prop": ["72878", "building.72878", "NULL", "NULL", "NULL", "NULL", "NULL", "NULL", "-1", "0", "-1", "NULL", "NULL", "w657096875", "657096875", "way", "yes", "NULL", "NULL", "NULL", "NULL", "NULL", "NULL", "NULL", "NULL", "NULL", "NULL", "NULL", "NULL", "NULL", "NULL", "NULL", "NULL", "NULL", "NULL", "NULL", "NULL", "NULL", "NULL", "NULL", "NULL", "NULL", "NULL", "NULL", "NULL", "NULL", "NULL", "NULL", "NULL", "NULL", "NULL", "NULL", "NULL", "NULL", "NULL", "NULL", "NULL", "NULL", "NULL", "NULL", "NULL", "NULL", "NULL", "NULL", "NULL", "NULL", "NULL", "NULL", "NULL", "NULL", "NULL", "NULL", "NULL", "NULL", "NULL", "NULL", "NULL", "NULL", "NULL", "NULL", "NULL", "NULL", "NULL", "NULL", "NULL", "NULL", "NULL", "NULL", "NULL", "NULL", "NULL", "NULL", "NULL", "NULL", "NULL", "NULL", "NULL", "NULL", "NULL", "NULL", "NULL", "NULL", "NULL", "NULL", "NULL", "NULL", "NULL", "NULL", "NULL", "NULL", "NULL", "NULL", "NULL", "NULL", "NULL", "NULL", "NULL", "NULL", "NULL", "NULL", "NULL", "NULL", "NULL", "NULL", "NULL", "NULL", "NULL", "NULL", "NULL", "NULL", "NULL", "NULL", "NULL", "NULL", "NULL", "NULL", "NULL", "NULL", "NULL", "NULL", "NULL", "NULL", "NULL", "NULL", "NULL", "NULL", "NULL", "NULL", "NULL", "NULL", "NULL", "NULL", "NULL", "NULL", "NULL", "NULL", "NULL", "NULL", "NULL", "NULL", "NULL", "NULL", "NULL", "NULL", "NULL", "NULL", "NULL", "NULL", "NULL", "NULL", "NULL", "NULL", "NULL", "NULL", "NULL", "NULL", "NULL", "NULL", "NULL", "NULL", "NULL", "NULL", "NULL", "NULL", "NULL", "NULL", "0.03956584319611874", "0.36250534256257827", "9.1620780268911"]}, {"geom": {"polygons": [[[[-0.05071181393086022, -0.05707147796678136], [-0.050699013930866954, -0.05705277796678132], [-0.05062991393086236, -0.05709657796678158], [-0.05064271393086983, -0.05711527796678162], [-0.05071181393086022, -0.05707147796678136]]]], "centroids": [[-0.0506708639308755, -0.05708402796678058, 0.0]], "h": 2.401241760652053e-06}, "mtl": {"idx": 0}, "prop": ["72879", "building.72879", "NULL", "NULL", "NULL", "NULL", "NULL", "NULL", "-1", "0", "-1", "NULL", "NULL", "w657096876", "657096876", "way", "yes", "NULL", "NULL", "NULL", "NULL", "NULL", "NULL", "NULL", "NULL", "NULL", "NULL", "NULL", "NULL", "NULL", "NULL", "NULL", "NULL", "NULL", "NULL", "NULL", "NULL", "NULL", "NULL", "NULL", "NULL", "NULL", "NULL", "NULL", "NULL", "NULL", "NULL", "NULL", "NULL", "NULL", "NULL", "NULL", "NULL", "NULL", "NULL", "NULL", "NULL", "NULL", "NULL", "NULL", "NULL", "NULL", "NULL", "NULL", "NULL", "NULL", "NULL", "NULL", "NULL", "NULL", "NULL", "NULL", "NULL", "NULL", "NULL", "NULL", "NULL", "NULL", "NULL", "NULL", "NULL", "NULL", "NULL", "NULL", "NULL", "NULL", "NULL", "NULL", "NULL", "NULL", "NULL", "NULL", "NULL", "NULL", "NULL", "NULL", "NULL", "NULL", "NULL", "NULL", "NULL", "NULL", "NULL", "NULL", "NULL", "NULL", "NULL", "NULL", "NULL", "NULL", "NULL", "NULL", "NULL", "NULL", "NULL", "NULL", "NULL", "NULL", "NULL", "NULL", "NULL", "NULL", "NULL", "NULL", "NULL", "NULL", "NULL", "NULL", "NULL", "NULL", "NULL", "NULL", "NULL", "NULL", "NULL", "NULL", "NULL", "NULL", "NULL", "NULL", "NULL", "NULL", "NULL", "NULL", "NULL", "NULL", "NULL", "NULL", "NULL", "NULL", "NULL", "NULL", "NULL", "NULL", "NULL", "NULL", "NULL", "NULL", "NULL", "NULL", "NULL", "NULL", "NULL", "NULL", "NULL", "NULL", "NULL", "NULL", "NULL", "NULL", "NULL", "NULL", "NULL", "NULL", "NULL", "NULL", "NULL", "NULL", "NULL", "NULL", "NULL", "NULL", "NULL", "NULL", "NULL", "NULL", "0.02401241760652053", "0.23790248059417424", "9.907477226681758"]}, {"geom": {"polygons": [[[[-0.050770813930867575, -0.057125577966781194], [-0.05073161393086423, -0.057073177966781685], [-0.05065051393086151, -0.0571292779667818], [-0.050689713930864855, -0.05718167796678131], [-0.050770813930867575, -0.057125577966781194]]]], "centroids": [[-0.050710663930857436, -0.05712742796678505, 0.0]], "h": 8.357592961067403e-06}, "mtl": {"idx": 0}, "prop": ["72880", "building.72880", "NULL", "NULL", "NULL", "NULL", "NULL", "NULL", "-1", "0", "-1", "NULL", "NULL", "w657096877", "657096877", "way", "yes", "NULL", "NULL", "NULL", "NULL", "NULL", "NULL", "NULL", "NULL", "NULL", "NULL", "NULL", "NULL", "NULL", "NULL", "NULL", "NULL", "NULL", "NULL", "NULL", "NULL", "NULL", "NULL", "NULL", "NULL", "NULL", "NULL", "NULL", "NULL", "NULL", "NULL", "NULL", "NULL", "NULL", "NULL", "NULL", "NULL", "NULL", "NULL", "NULL", "NULL", "NULL", "NULL", "NULL", "NULL", "NULL", "NULL", "NULL", "NULL", "NULL", "NULL", "NULL", "NULL", "NULL", "NULL", "NULL", "NULL", "NULL", "NULL", "NULL", "NULL", "NULL", "NULL", "NULL", "NULL", "NULL", "NULL", "NULL", "NULL", "NULL", "NULL", "NULL", "NULL", "NULL", "NULL", "NULL", "NULL", "NULL", "NULL", "NULL", "NULL", "NULL", "NULL", "NULL", "NULL", "NULL", "NULL", "NULL", "NULL", "NULL", "NULL", "NULL", "NULL", "NULL", "NULL", "NULL", "NULL", "NULL", "NULL", "NULL", "NULL", "NULL", "NULL", "NULL", "NULL", "NULL", "NULL", "NULL", "NULL", "NULL", "NULL", "NULL", "NULL", "NULL", "NULL", "NULL", "NULL", "NULL", "NULL", "NULL", "NULL", "NULL", "NULL", "NULL", "NULL", "NULL", "NULL", "NULL", "NULL", "NULL", "NULL", "NULL", "NULL", "NULL", "NULL", "NULL", "NULL", "NULL", "NULL", "NULL", "NULL", "NULL", "NULL", "NULL", "NULL", "NULL", "NULL", "NULL", "NULL", "NULL", "NULL", "NULL", "NULL", "NULL", "NULL", "NULL", "NULL", "NULL", "NULL", "NULL", "NULL", "NULL", "NULL", "NULL", "NULL", "NULL", "NULL", "NULL", "NULL", "NULL", "0.08357592961067402", "0.8357592961067402", "10"]}, {"geom": {"polygons": [[[[-0.0505790139308715, -0.056882577966781867], [-0.0505477139308681, -0.056861177966780474], [-0.05050471393086298, -0.056919177966781476], [-0.05053611393086044, -0.05694057796678109], [-0.0505790139308715, -0.056882577966781867]]]], "centroids": [[-0.05054187930508647, -0.05690088681340022, 0.0]], "h": 3.5477092795989597e-06}, "mtl": {"idx": 0}, "prop": ["72889", "building.72889", "NULL", "NULL", "NULL", "NULL", "NULL", "NULL", "-1", "0", "-1", "NULL", "NULL", "w657096886", "657096886", "way", "yes", "NULL", "NULL", "NULL", "NULL", "NULL", "NULL", "NULL", "NULL", "NULL", "NULL", "NULL", "NULL", "NULL", "NULL", "NULL", "NULL", "NULL", "NULL", "NULL", "NULL", "NULL", "NULL", "NULL", "NULL", "NULL", "NULL", "NULL", "NULL", "NULL", "NULL", "NULL", "NULL", "NULL", "NULL", "NULL", "NULL", "NULL", "NULL", "NULL", "NULL", "NULL", "NULL", "NULL", "NULL", "NULL", "NULL", "NULL", "NULL", "NULL", "NULL", "NULL", "NULL", "NULL", "NULL", "NULL", "NULL", "NULL", "NULL", "NULL", "NULL", "NULL", "NULL", "NULL", "NULL", "NULL", "NULL", "NULL", "NULL", "NULL", "NULL", "NULL", "NULL", "NULL", "NULL", "NULL", "NULL", "NULL", "NULL", "NULL", "NULL", "NULL", "NULL", "NULL", "NULL", "NULL", "NULL", "NULL", "NULL", "NULL", "NULL", "NULL", "NULL", "NULL", "NULL", "NULL", "NULL", "NULL", "NULL", "NULL", "NULL", "NULL", "NULL", "NULL", "NULL", "NULL", "NULL", "NULL", "NULL", "NULL", "NULL", "NULL", "NULL", "NULL", "NULL", "NULL", "NULL", "NULL", "NULL", "NULL", "NULL", "NULL", "NULL", "NULL", "NULL", "NULL", "NULL", "NULL", "NULL", "NULL", "NULL", "NULL", "NULL", "NULL", "NULL", "NULL", "NULL", "NULL", "NULL", "NULL", "NULL", "NULL", "NULL", "NULL", "NULL", "NULL", "NULL", "NULL", "NULL", "NULL", "NULL", "NULL", "NULL", "NULL", "NULL", "NULL", "NULL", "NULL", "NULL", "NULL", "NULL", "NULL", "NULL", "NULL", "NULL", "NULL", "NULL", "NULL", "NULL", "NULL", "0.035477092795989595", "0.321679825356827", "9.067254388814812"]}, {"geom": {"polygons": [[[[-0.050674213930861356, -0.05689737796678074], [-0.05065171393086132, -0.05687257796678047], [-0.050614813930863534, -0.05690347796678097], [-0.050637413930871844, -0.05692837796678063], [-0.050674213930861356, -0.05689737796678074]]]], "centroids": [[-0.050644525760404235, -0.05690046350841449, 0.0]], "h": 2.0912839196607314e-06}, "mtl": {"idx": 0}, "prop": ["72890", "building.72890", "NULL", "NULL", "NULL", "NULL", "NULL", "NULL", "-1", "0", "-1", "NULL", "NULL", "w657096887", "657096887", "way", "yes", "NULL", "NULL", "NULL", "NULL", "NULL", "NULL", "NULL", "NULL", "NULL", "NULL", "NULL", "NULL", "NULL", "NULL", "NULL", "NULL", "NULL", "NULL", "NULL", "NULL", "NULL", "NULL", "NULL", "NULL", "NULL", "NULL", "NULL", "NULL", "NULL", "NULL", "NULL", "NULL", "NULL", "NULL", "NULL", "NULL", "NULL", "NULL", "NULL", "NULL", "NULL", "NULL", "NULL", "NULL", "NULL", "NULL", "NULL", "NULL", "NULL", "NULL", "NULL", "NULL", "NULL", "NULL", "NULL", "NULL", "NULL", "NULL", "NULL", "NULL", "NULL", "NULL", "NULL", "NULL", "NULL", "NULL", "NULL", "NULL", "NULL", "NULL", "NULL", "NULL", "NULL", "NULL", "NULL", "NULL", "NULL", "NULL", "NULL", "NULL", "NULL", "NULL", "NULL", "NULL", "NULL", "NULL", "NULL", "NULL", "NULL", "NULL", "NULL", "NULL", "NULL", "NULL", "NULL", "NULL", "NULL", "NULL", "NULL", "NULL", "NULL", "NULL", "NULL", "NULL", "NULL", "NULL", "NULL", "NULL", "NULL", "NULL", "NULL", "NULL", "NULL", "NULL", "NULL", "NULL", "NULL", "NULL", "NULL", "NULL", "NULL", "NULL", "NULL", "NULL", "NULL", "NULL", "NULL", "NULL", "NULL", "NULL", "NULL", "NULL", "NULL", "NULL", "NULL", "NULL", "NULL", "NULL", "NULL", "NULL", "NULL", "NULL", "NULL", "NULL", "NULL", "NULL", "NULL", "NULL", "NULL", "NULL", "NULL", "NULL", "NULL", "NULL", "NULL", "NULL", "NULL", "NULL", "NULL", "NULL", "NULL", "NULL", "NULL", "NULL", "NULL", "NULL", "NULL", "NULL", "NULL", "0.020912839196607313", "0.1882155527694658", "9"]}, {"geom": {"polygons": [[[[-0.05073331393086278, -0.056937977966780906], [-0.05069291393085962, -0.056895077966780505], [-0.05065061393086978, -0.056931877966780675], [-0.05069101393087294, -0.056974777966781076], [-0.05073331393086278, -0.056937977966780906]]]], "centroids": [[-0.050691963930859174, -0.05693492796678079, 0.0]], "h": 4.278601438769091e-06}, "mtl": {"idx": 0}, "prop": ["72891", "building.72891", "NULL", "NULL", "NULL", "NULL", "NULL", "NULL", "-1", "0", "-1", "NULL", "NULL", "w657096888", "657096888", "way", "yes", "NULL", "NULL", "NULL", "NULL", "NULL", "NULL", "NULL", "NULL", "NULL", "NULL", "NULL", "NULL", "NULL", "NULL", "NULL", "NULL", "NULL", "NULL", "NULL", "NULL", "NULL", "NULL", "NULL", "NULL", "NULL", "NULL", "NULL", "NULL", "NULL", "NULL", "NULL", "NULL", "NULL", "NULL", "NULL", "NULL", "NULL", "NULL", "NULL", "NULL", "NULL", "NULL", "NULL", "NULL", "NULL", "NULL", "NULL", "NULL", "NULL", "NULL", "NULL", "NULL", "NULL", "NULL", "NULL", "NULL", "NULL", "NULL", "NULL", "NULL", "NULL", "NULL", "NULL", "NULL", "NULL", "NULL", "NULL", "NULL", "NULL", "NULL", "NULL", "NULL", "NULL", "NULL", "NULL", "NULL", "NULL", "NULL", "NULL", "NULL", "NULL", "NULL", "NULL", "NULL", "NULL", "NULL", "NULL", "NULL", "NULL", "NULL", "NULL", "NULL", "NULL", "NULL", "NULL", "NULL", "NULL", "NULL", "NULL", "NULL", "NULL", "NULL", "NULL", "NULL", "NULL", "NULL", "NULL", "NULL", "NULL", "NULL", "NULL", "NULL", "NULL", "NULL", "NULL", "NULL", "NULL", "NULL", "NULL", "NULL", "NULL", "NULL", "NULL", "NULL", "NULL", "NULL", "NULL", "NULL", "NULL", "NULL", "NULL", "NULL", "NULL", "NULL", "NULL", "NULL", "NULL", "NULL", "NULL", "NULL", "NULL", "NULL", "NULL", "NULL", "NULL", "NULL", "NULL", "NULL", "NULL", "NULL", "NULL", "NULL", "NULL", "NULL", "NULL", "NULL", "NULL", "NULL", "NULL", "NULL", "NULL", "NULL", "NULL", "NULL", "NULL", "NULL", "NULL", "NULL", "NULL", "0.042786014387690904", "0.38507412948921815", "9"]}, {"geom": {"polygons": [[[[-0.050799013930870274, -0.056868377966781125], [-0.05078131393086949, -0.05684407796678137], [-0.05071891393086503, -0.05688597796678074], [-0.050736613930865815, -0.0569102779667805], [-0.050799013930870274, -0.056868377966781125]]]], "centroids": [[-0.050758963930860546, -0.056877177966780934, 0.0]], "h": 2.9263031989992954e-06}, "mtl": {"idx": 0}, "prop": ["72892", "building.72892", "NULL", "NULL", "NULL", "NULL", "NULL", "NULL", "-1", "0", "-1", "NULL", "NULL", "w657096889", "657096889", "way", "yes", "NULL", "NULL", "NULL", "NULL", "NULL", "NULL", "NULL", "NULL", "NULL", "NULL", "NULL", "NULL", "NULL", "NULL", "NULL", "NULL", "NULL", "NULL", "NULL", "NULL", "NULL", "NULL", "NULL", "NULL", "NULL", "NULL", "NULL", "NULL", "NULL", "NULL", "NULL", "NULL", "NULL", "NULL", "NULL", "NULL", "NULL", "NULL", "NULL", "NULL", "NULL", "NULL", "NULL", "NULL", "NULL", "NULL", "NULL", "NULL", "NULL", "NULL", "NULL", "NULL", "NULL", "NULL", "NULL", "NULL", "NULL", "NULL", "NULL", "NULL", "NULL", "NULL", "NULL", "NULL", "NULL", "NULL", "NULL", "NULL", "NULL", "NULL", "NULL", "NULL", "NULL", "NULL", "NULL", "NULL", "NULL", "NULL", "NULL", "NULL", "NULL", "NULL", "NULL", "NULL", "NULL", "NULL", "NULL", "NULL", "NULL", "NULL", "NULL", "NULL", "NULL", "NULL", "NULL", "NULL", "NULL", "NULL", "NULL", "NULL", "NULL", "NULL", "NULL", "NULL", "NULL", "NULL", "NULL", "NULL", "NULL", "NULL", "NULL", "NULL", "NULL", "NULL", "NULL", "NULL", "NULL", "NULL", "NULL", "NULL", "NULL", "NULL", "NULL", "NULL", "NULL", "NULL", "NULL", "NULL", "NULL", "NULL", "NULL", "NULL", "NULL", "NULL", "NULL", "NULL", "NULL", "NULL", "NULL", "NULL", "NULL", "NULL", "NULL", "NULL", "NULL", "NULL", "NULL", "NULL", "NULL", "NULL", "NULL", "NULL", "NULL", "NULL", "NULL", "NULL", "NULL", "NULL", "NULL", "NULL", "NULL", "NULL", "NULL", "NULL", "NULL", "NULL", "NULL", "NULL", "NULL", "0.029263031989992954", "0.26336728790993663", "9.000000000000002"]}, {"geom": {"polygons": [[[[-0.05082441393086867, -0.05690967796678059], [-0.05080031393086415, -0.056879177966781214], [-0.05075541393087235, -0.05691207796678199], [-0.05077951393086266, -0.05694247796678198], [-0.05082441393086867, -0.05690967796678059]]]], "centroids": [[-0.05078991947075906, -0.05691084444075756, 0.0]], "h": 2.797921438222412e-06}, "mtl": {"idx": 0}, "prop": ["72893", "building.72893", "NULL", "NULL", "NULL", "NULL", "NULL", "NULL", "-1", "0", "-1", "NULL", "NULL", "w657096890", "657096890", "way", "yes", "NULL", "NULL", "NULL", "NULL", "NULL", "NULL", "NULL", "NULL", "NULL", "NULL", "NULL", "NULL", "NULL", "NULL", "NULL", "NULL", "NULL", "NULL", "NULL", "NULL", "NULL", "NULL", "NULL", "NULL", "NULL", "NULL", "NULL", "NULL", "NULL", "NULL", "NULL", "NULL", "NULL", "NULL", "NULL", "NULL", "NULL", "NULL", "NULL", "NULL", "NULL", "NULL", "NULL", "NULL", "NULL", "NULL", "NULL", "NULL", "NULL", "NULL", "NULL", "NULL", "NULL", "NULL", "NULL", "NULL", "NULL", "NULL", "NULL", "NULL", "NULL", "NULL", "NULL", "NULL", "NULL", "NULL", "NULL", "NULL", "NULL", "NULL", "NULL", "NULL", "NULL", "NULL", "NULL", "NULL", "NULL", "NULL", "NULL", "NULL", "NULL", "NULL", "NULL", "NULL", "NULL", "NULL", "NULL", "NULL", "NULL", "NULL", "NULL", "NULL", "NULL", "NULL", "NULL", "NULL", "NULL", "NULL", "NULL", "NULL", "NULL", "NULL", "NULL", "NULL", "NULL", "NULL", "NULL", "NULL", "NULL", "NULL", "NULL", "NULL", "NULL", "NULL", "NULL", "NULL", "NULL", "NULL", "NULL", "NULL", "NULL", "NULL", "NULL", "NULL", "NULL", "NULL", "NULL", "NULL", "NULL", "NULL", "NULL", "NULL", "NULL", "NULL", "NULL", "NULL", "NULL", "NULL", "NULL", "NULL", "NULL", "NULL", "NULL", "NULL", "NULL", "NULL", "NULL", "NULL", "NULL", "NULL", "NULL", "NULL", "NULL", "NULL", "NULL", "NULL", "NULL", "NULL", "NULL", "NULL", "NULL", "NULL", "NULL", "NULL", "NULL", "NULL", "NULL", "NULL", "NULL", "0.027979214382224123", "0.2518129294400171", "9"]}, {"geom": {"polygons": [[[[-0.050871413930863696, -0.05686327796678192], [-0.05083031393085946, -0.056806877966781855], [-0.050792013930859525, -0.056832677966781375], [-0.050833213930872034, -0.056888977966780274], [-0.050871413930863696, -0.05686327796678192]]]], "centroids": [[-0.05083172977069239, -0.05684793789161269, 0.0]], "h": 4.166639999297994e-06}, "mtl": {"idx": 0}, "prop": ["72894", "building.72894", "NULL", "NULL", "NULL", "NULL", "NULL", "NULL", "-1", "0", "-1", "NULL", "NULL", "w657096891", "657096891", "way", "yes", "NULL", "NULL", "NULL", "NULL", "NULL", "NULL", "NULL", "NULL", "NULL", "NULL", "NULL", "NULL", "NULL", "NULL", "NULL", "NULL", "NULL", "NULL", "NULL", "NULL", "NULL", "NULL", "NULL", "NULL", "NULL", "NULL", "NULL", "NULL", "NULL", "NULL", "NULL", "NULL", "NULL", "NULL", "NULL", "NULL", "NULL", "NULL", "NULL", "NULL", "NULL", "NULL", "NULL", "NULL", "NULL", "NULL", "NULL", "NULL", "NULL", "NULL", "NULL", "NULL", "NULL", "NULL", "NULL", "NULL", "NULL", "NULL", "NULL", "NULL", "NULL", "NULL", "NULL", "NULL", "NULL", "NULL", "NULL", "NULL", "NULL", "NULL", "NULL", "NULL", "NULL", "NULL", "NULL", "NULL", "NULL", "NULL", "NULL", "NULL", "NULL", "NULL", "NULL", "NULL", "NULL", "NULL", "NULL", "NULL", "NULL", "NULL", "NULL", "NULL", "NULL", "NULL", "NULL", "NULL", "NULL", "NULL", "NULL", "NULL", "NULL", "NULL", "NULL", "NULL", "NULL", "NULL", "NULL", "NULL", "NULL", "NULL", "NULL", "NULL", "NULL", "NULL", "NULL", "NULL", "NULL", "NULL", "NULL", "NULL", "NULL", "NULL", "NULL", "NULL", "NULL", "NULL", "NULL", "NULL", "NULL", "NULL", "NULL", "NULL", "NULL", "NULL", "NULL", "NULL", "NULL", "NULL", "NULL", "NULL", "NULL", "NULL", "NULL", "NULL", "NULL", "NULL", "NULL", "NULL", "NULL", "NULL", "NULL", "NULL", "NULL", "NULL", "NULL", "NULL", "NULL", "NULL", "NULL", "NULL", "NULL", "NULL", "NULL", "NULL", "NULL", "NULL", "NULL", "NULL", "NULL", "0.041666399992979934", "0.3749975999368194", "9"]}, {"geom": {"polygons": [[[[-0.050870013930861546, -0.056666677966781265], [-0.050843213930861, -0.056640877966781744], [-0.050807013930864287, -0.056675677966781635], [-0.050833813930864835, -0.056701477966781155], [-0.050870013930861546, -0.056666677966781265]]]], "centroids": [[-0.05083851393087002, -0.056671177966778785, 0.0]], "h": 2.4191135994382686e-06}, "mtl": {"idx": 0}, "prop": ["72899", "building.72899", "NULL", "NULL", "NULL", "NULL", "NULL", "NULL", "-1", "0", "-1", "NULL", "NULL", "w657096896", "657096896", "way", "yes", "NULL", "NULL", "NULL", "NULL", "NULL", "NULL", "NULL", "NULL", "NULL", "NULL", "NULL", "NULL", "NULL", "NULL", "NULL", "NULL", "NULL", "NULL", "NULL", "NULL", "NULL", "NULL", "NULL", "NULL", "NULL", "NULL", "NULL", "NULL", "NULL", "NULL", "NULL", "NULL", "NULL", "NULL", "NULL", "NULL", "NULL", "NULL", "NULL", "NULL", "NULL", "NULL", "NULL", "NULL", "NULL", "NULL", "NULL", "NULL", "NULL", "NULL", "NULL", "NULL", "NULL", "NULL", "NULL", "NULL", "NULL", "NULL", "NULL", "NULL", "NULL", "NULL", "NULL", "NULL", "NULL", "NULL", "NULL", "NULL", "NULL", "NULL", "NULL", "NULL", "NULL", "NULL", "NULL", "NULL", "NULL", "NULL", "NULL", "NULL", "NULL", "NULL", "NULL", "NULL", "NULL", "NULL", "NULL", "NULL", "NULL", "NULL", "NULL", "NULL", "NULL", "NULL", "NULL", "NULL", "NULL", "NULL", "NULL", "NULL", "NULL", "NULL", "NULL", "NULL", "NULL", "NULL", "NULL", "NULL", "NULL", "NULL", "NULL", "NULL", "NULL", "NULL", "NULL", "NULL", "NULL", "NULL", "NULL", "NULL", "NULL", "NULL", "NULL", "NULL", "NULL", "NULL", "NULL", "NULL", "NULL", "NULL", "NULL", "NULL", "NULL", "NULL", "NULL", "NULL", "NULL", "NULL", "NULL", "NULL", "NULL", "NULL", "NULL", "NULL", "NULL", "NULL", "NULL", "NULL", "NULL", "NULL", "NULL", "NULL", "NULL", "NULL", "NULL", "NULL", "NULL", "NULL", "NULL", "NULL", "NULL", "NULL", "NULL", "NULL", "NULL", "NULL", "NULL", "NULL", "NULL", "0.024191135994382683", "0.21772022394944415", "9"]}, {"geom": {"polygons": [[[[-0.050871113930867295, -0.05674497796678146], [-0.050842313930871796, -0.056711577966781945], [-0.050799013930870274, -0.05674607796678188], [-0.05082781393086577, -0.0567794779667814], [-0.050871113930867295, -0.05674497796678146]]]], "centroids": [[-0.05083506393084747, -0.056745527966780784, 0.0]], "h": 3.1620067198644e-06}, "mtl": {"idx": 0}, "prop": ["72901", "building.72901", "NULL", "NULL", "NULL", "NULL", "NULL", "NULL", "-1", "0", "-1", "NULL", "NULL", "w657096898", "657096898", "way", "yes", "NULL", "NULL", "NULL", "NULL", "NULL", "NULL", "NULL", "NULL", "NULL", "NULL", "NULL", "NULL", "NULL", "NULL", "NULL", "NULL", "NULL", "NULL", "NULL", "NULL", "NULL", "NULL", "NULL", "NULL", "NULL", "NULL", "NULL", "NULL", "NULL", "NULL", "NULL", "NULL", "NULL", "NULL", "NULL", "NULL", "NULL", "NULL", "NULL", "NULL", "NULL", "NULL", "NULL", "NULL", "NULL", "NULL", "NULL", "NULL", "NULL", "NULL", "NULL", "NULL", "NULL", "NULL", "NULL", "NULL", "NULL", "NULL", "NULL", "NULL", "NULL", "NULL", "NULL", "NULL", "NULL", "NULL", "NULL", "NULL", "NULL", "NULL", "NULL", "NULL", "NULL", "NULL", "NULL", "NULL", "NULL", "NULL", "NULL", "NULL", "NULL", "NULL", "NULL", "NULL", "NULL", "NULL", "NULL", "NULL", "NULL", "NULL", "NULL", "NULL", "NULL", "NULL", "NULL", "NULL", "NULL", "NULL", "NULL", "NULL", "NULL", "NULL", "NULL", "NULL", "NULL", "NULL", "NULL", "NULL", "NULL", "NULL", "NULL", "NULL", "NULL", "NULL", "NULL", "NULL", "NULL", "NULL", "NULL", "NULL", "NULL", "NULL", "NULL", "NULL", "NULL", "NULL", "NULL", "NULL", "NULL", "NULL", "NULL", "NULL", "NULL", "NULL", "NULL", "NULL", "NULL", "NULL", "NULL", "NULL", "NULL", "NULL", "NULL", "NULL", "NULL", "NULL", "NULL", "NULL", "NULL", "NULL", "NULL", "NULL", "NULL", "NULL", "NULL", "NULL", "NULL", "NULL", "NULL", "NULL", "NULL", "NULL", "NULL", "NULL", "NULL", "NULL", "NULL", "NULL", "NULL", "0.031620067198644", "0.284580604787796", "9"]}, {"geom": {"polygons": [[[[-0.05082241393085951, -0.05671397796678157], [-0.05080371393086125, -0.0566929779667813], [-0.05076341393086636, -0.056726177966780256], [-0.0507822139308729, -0.056747177966780527], [-0.05082241393085951, -0.05671397796678157]]]], "centroids": [[-0.050792929108268936, -0.05672008172105336, 0.0]], "h": 1.902203998440701e-06}, "mtl": {"idx": 0}, "prop": ["72902", "building.72902", "NULL", "NULL", "NULL", "NULL", "NULL", "NULL", "-1", "0", "-1", "NULL", "NULL", "w657096899", "657096899", "way", "yes", "NULL", "NULL", "NULL", "NULL", "NULL", "NULL", "NULL", "NULL", "NULL", "NULL", "NULL", "NULL", "NULL", "NULL", "NULL", "NULL", "NULL", "NULL", "NULL", "NULL", "NULL", "NULL", "NULL", "NULL", "NULL", "NULL", "NULL", "NULL", "NULL", "NULL", "NULL", "NULL", "NULL", "NULL", "NULL", "NULL", "NULL", "NULL", "NULL", "NULL", "NULL", "NULL", "NULL", "NULL", "NULL", "NULL", "NULL", "NULL", "NULL", "NULL", "NULL", "NULL", "NULL", "NULL", "NULL", "NULL", "NULL", "NULL", "NULL", "NULL", "NULL", "NULL", "NULL", "NULL", "NULL", "NULL", "NULL", "NULL", "NULL", "NULL", "NULL", "NULL", "NULL", "NULL", "NULL", "NULL", "NULL", "NULL", "NULL", "NULL", "NULL", "NULL", "NULL", "NULL", "NULL", "NULL", "NULL", "NULL", "NULL", "NULL", "NULL", "NULL", "NULL", "NULL", "NULL", "NULL", "NULL", "NULL", "NULL", "NULL", "NULL", "NULL", "NULL", "NULL", "NULL", "NULL", "NULL", "NULL", "NULL", "NULL", "NULL", "NULL", "NULL", "NULL", "NULL", "NULL", "NULL", "NULL", "NULL", "NULL", "NULL", "NULL", "NULL", "NULL", "NULL", "NULL", "NULL", "NULL", "NULL", "NULL", "NULL", "NULL", "NULL", "NULL", "NULL", "NULL", "NULL", "NULL", "NULL", "NULL", "NULL", "NULL", "NULL", "NULL", "NULL", "NULL", "NULL", "NULL", "NULL", "NULL", "NULL", "NULL", "NULL", "NULL", "NULL", "NULL", "NULL", "NULL", "NULL", "NULL", "NULL", "NULL", "NULL", "NULL", "NULL", "NULL", "NULL", "NULL", "NULL", "0.01902203998440701", "0.17119835985966309", "9"]}, {"geom": {"polygons": [[[[-0.050776213930859626, -0.056763977966781454], [-0.050747913930862865, -0.05673857796678128], [-0.050719113930867366, -0.056768277966781966], [-0.050747313930870064, -0.05679357796678097], [-0.050776213930859626, -0.056763977966781454]]]], "centroids": [[-0.050747647459871814, -0.056766093363606274, 0.0]], "h": 2.033372159427757e-06}, "mtl": {"idx": 0}, "prop": ["72903", "building.72903", "NULL", "NULL", "NULL", "NULL", "NULL", "NULL", "-1", "0", "-1", "NULL", "NULL", "w657096900", "657096900", "way", "yes", "NULL", "NULL", "NULL", "NULL", "NULL", "NULL", "NULL", "NULL", "NULL", "NULL", "NULL", "NULL", "NULL", "NULL", "NULL", "NULL", "NULL", "NULL", "NULL", "NULL", "NULL", "NULL", "NULL", "NULL", "NULL", "NULL", "NULL", "NULL", "NULL", "NULL", "NULL", "NULL", "NULL", "NULL", "NULL", "NULL", "NULL", "NULL", "NULL", "NULL", "NULL", "NULL", "NULL", "NULL", "NULL", "NULL", "NULL", "NULL", "NULL", "NULL", "NULL", "NULL", "NULL", "NULL", "NULL", "NULL", "NULL", "NULL", "NULL", "NULL", "NULL", "NULL", "NULL", "NULL", "NULL", "NULL", "NULL", "NULL", "NULL", "NULL", "NULL", "NULL", "NULL", "NULL", "NULL", "NULL", "NULL", "NULL", "NULL", "NULL", "NULL", "NULL", "NULL", "NULL", "NULL", "NULL", "NULL", "NULL", "NULL", "NULL", "NULL", "NULL", "NULL", "NULL", "NULL", "NULL", "NULL", "NULL", "NULL", "NULL", "NULL", "NULL", "NULL", "NULL", "NULL", "NULL", "NULL", "NULL", "NULL", "NULL", "NULL", "NULL", "NULL", "NULL", "NULL", "NULL", "NULL", "NULL", "NULL", "NULL", "NULL", "NULL", "NULL", "NULL", "NULL", "NULL", "NULL", "NULL", "NULL", "NULL", "NULL", "NULL", "NULL", "NULL", "NULL", "NULL", "NULL", "NULL", "NULL", "NULL", "NULL", "NULL", "NULL", "NULL", "NULL", "NULL", "NULL", "NULL", "NULL", "NULL", "NULL", "NULL", "NULL", "NULL", "NULL", "NULL", "NULL", "NULL", "NULL", "NULL", "NULL", "NULL", "NULL", "NULL", "NULL", "NULL", "NULL", "NULL", "NULL", "0.020333721594277567", "0.1830034943484981", "9"]}, {"geom": {"polygons": [[[[-0.05071251393086129, -0.05674337796678053], [-0.05067941393086528, -0.05671207796678068], [-0.05064181393086642, -0.05674887796678085], [-0.05067491393086243, -0.056780077966781306], [-0.05071251393086129, -0.05674337796678053]]]], "centroids": [[-0.05067716503951658, -0.056746094547202475, 0.0]], "h": 3.099286799825577e-06}, "mtl": {"idx": 0}, "prop": ["72904", "building.72904", "NULL", "NULL", "NULL", "NULL", "NULL", "NULL", "-1", "0", "-1", "NULL", "NULL", "w657096901", "657096901", "way", "yes", "NULL", "NULL", "NULL", "NULL", "NULL", "NULL", "NULL", "NULL", "NULL", "NULL", "NULL", "NULL", "NULL", "NULL", "NULL", "NULL", "NULL", "NULL", "NULL", "NULL", "NULL", "NULL", "NULL", "NULL", "NULL", "NULL", "NULL", "NULL", "NULL", "NULL", "NULL", "NULL", "NULL", "NULL", "NULL", "NULL", "NULL", "NULL", "NULL", "NULL", "NULL", "NULL", "NULL", "NULL", "NULL", "NULL", "NULL", "NULL", "NULL", "NULL", "NULL", "NULL", "NULL", "NULL", "NULL", "NULL", "NULL", "NULL", "NULL", "NULL", "NULL", "NULL", "NULL", "NULL", "NULL", "NULL", "NULL", "NULL", "NULL", "NULL", "NULL", "NULL", "NULL", "NULL", "NULL", "NULL", "NULL", "NULL", "NULL", "NULL", "NULL", "NULL", "NULL", "NULL", "NULL", "NULL", "NULL", "NULL", "NULL", "NULL", "NULL", "NULL", "NULL", "NULL", "NULL", "NULL", "NULL", "NULL", "NULL", "NULL", "NULL", "NULL", "NULL", "NULL", "NULL", "NULL", "NULL", "NULL", "NULL", "NULL", "NULL", "NULL", "NULL", "NULL", "NULL", "NULL", "NULL", "NULL", "NULL", "NULL", "NULL", "NULL", "NULL", "NULL", "NULL", "NULL", "NULL", "NULL", "NULL", "NULL", "NULL", "NULL", "NULL", "NULL", "NULL", "NULL", "NULL", "NULL", "NULL", "NULL", "NULL", "NULL", "NULL", "NULL", "NULL", "NULL", "NULL", "NULL", "NULL", "NULL", "NULL", "NULL", "NULL", "NULL", "NULL", "NULL", "NULL", "NULL", "NULL", "NULL", "NULL", "NULL", "NULL", "NULL", "NULL", "NULL", "NULL", "NULL", "NULL", "0.03099286799825577", "0.27893581198430195", "9"]}, {"geom": {"polygons": [[[[-0.05079431393086509, -0.05666987796678136], [-0.05076071393087034, -0.05663637796678067], [-0.05068761393086163, -0.05670407796678134], [-0.05072121393087059, -0.05673757796678203], [-0.05079431393086509, -0.05666987796678136]]]], "centroids": [[-0.05074096393086336, -0.05668697796678046, 0.0]], "h": 6.121746720542692e-06}, "mtl": {"idx": 0}, "prop": ["72905", "building.72905", "NULL", "NULL", "NULL", "NULL", "NULL", "NULL", "-1", "0", "-1", "NULL", "NULL", "w657096902", "657096902", "way", "yes", "NULL", "NULL", "NULL", "NULL", "NULL", "NULL", "NULL", "NULL", "NULL", "NULL", "NULL", "NULL", "NULL", "NULL", "NULL", "NULL", "NULL", "NULL", "NULL", "NULL", "NULL", "NULL", "NULL", "NULL", "NULL", "NULL", "NULL", "NULL", "NULL", "NULL", "NULL", "NULL", "NULL", "NULL", "NULL", "NULL", "NULL", "NULL", "NULL", "NULL", "NULL", "NULL", "NULL", "NULL", "NULL", "NULL", "NULL", "NULL", "NULL", "NULL", "NULL", "NULL", "NULL", "NULL", "NULL", "NULL", "NULL", "NULL", "NULL", "NULL", "NULL", "NULL", "NULL", "NULL", "NULL", "NULL", "NULL", "NULL", "NULL", "NULL", "NULL", "NULL", "NULL", "NULL", "NULL", "NULL", "NULL", "NULL", "NULL", "NULL", "NULL", "NULL", "NULL", "NULL", "NULL", "NULL", "NULL", "NULL", "NULL", "NULL", "NULL", "NULL", "NULL", "NULL", "NULL", "NULL", "NULL", "NULL", "NULL", "NULL", "NULL", "NULL", "NULL", "NULL", "NULL", "NULL", "NULL", "NULL", "NULL", "NULL", "NULL", "NULL", "NULL", "NULL", "NULL", "NULL", "NULL", "NULL", "NULL", "NULL", "NULL", "NULL", "NULL", "NULL", "NULL", "NULL", "NULL", "NULL", "NULL", "NULL", "NULL", "NULL", "NULL", "NULL", "NULL", "NULL", "NULL", "NULL", "NULL", "NULL", "NULL", "NULL", "NULL", "NULL", "NULL", "NULL", "NULL", "NULL", "NULL", "NULL", "NULL", "NULL", "NULL", "NULL", "NULL", "NULL", "NULL", "NULL", "NULL", "NULL", "NULL", "NULL", "NULL", "NULL", "NULL", "NULL", "NULL", "NULL", "NULL", "0.061217467205426916", "0.5509572048488423", "9"]}, {"geom": {"polygons": [[[[-0.050833213930872034, -0.05663767796678165], [-0.050755013930867676, -0.056562577966781546], [-0.05072691393087325, -0.05658957796678088], [-0.050805013930869336, -0.056664677966780985], [-0.050833213930872034, -0.05663767796678165]]]], "centroids": [[-0.050780052008775556, -0.05661363765522154, 0.0]], "h": 5.474453038388428e-06}, "mtl": {"idx": 0}, "prop": ["72906", "building.72906", "NULL", "NULL", "NULL", "NULL", "NULL", "NULL", "-1", "0", "-1", "NULL", "NULL", "w657096903", "657096903", "way", "yes", "NULL", "NULL", "NULL", "NULL", "NULL", "NULL", "NULL", "NULL", "NULL", "NULL", "NULL", "NULL", "NULL", "NULL", "NULL", "NULL", "NULL", "NULL", "NULL", "NULL", "NULL", "NULL", "NULL", "NULL", "NULL", "NULL", "NULL", "NULL", "NULL", "NULL", "NULL", "NULL", "NULL", "NULL", "NULL", "NULL", "NULL", "NULL", "NULL", "NULL", "NULL", "NULL", "NULL", "NULL", "NULL", "NULL", "NULL", "NULL", "NULL", "NULL", "NULL", "NULL", "NULL", "NULL", "NULL", "NULL", "NULL", "NULL", "NULL", "NULL", "NULL", "NULL", "NULL", "NULL", "NULL", "NULL", "NULL", "NULL", "NULL", "NULL", "NULL", "NULL", "NULL", "NULL", "NULL", "NULL", "NULL", "NULL", "NULL", "NULL", "NULL", "NULL", "NULL", "NULL", "NULL", "NULL", "NULL", "NULL", "NULL", "NULL", "NULL", "NULL", "NULL", "NULL", "NULL", "NULL", "NULL", "NULL", "NULL", "NULL", "NULL", "NULL", "NULL", "NULL", "NULL", "NULL", "NULL", "NULL", "NULL", "NULL", "NULL", "NULL", "NULL", "NULL", "NULL", "NULL", "NULL", "NULL", "NULL", "NULL", "NULL", "NULL", "NULL", "NULL", "NULL", "NULL", "NULL", "NULL", "NULL", "NULL", "NULL", "NULL", "NULL", "NULL", "NULL", "NULL", "NULL", "NULL", "NULL", "NULL", "NULL", "NULL", "NULL", "NULL", "NULL", "NULL", "NULL", "NULL", "NULL", "NULL", "NULL", "NULL", "NULL", "NULL", "NULL", "NULL", "NULL", "NULL", "NULL", "NULL", "NULL", "NULL", "NULL", "NULL", "NULL", "NULL", "NULL", "NULL", "NULL", "0.05474453038388428", "0.4927007734549585", "9"]}, {"geom": {"polygons": [[[[-0.05086871393086767, -0.056609277966781946], [-0.05082821393087045, -0.05657437796678089], [-0.050804813930867, -0.05659947796678111], [-0.05084521393087016, -0.05663437796678039], [-0.05086871393086767, -0.056609277966781946]]]], "centroids": [[-0.05083674802132521, -0.056604380638972884, 0.0]], "h": 2.376475200283115e-06}, "mtl": {"idx": 0}, "prop": ["72907", "building.72907", "NULL", "NULL", "NULL", "NULL", "NULL", "NULL", "-1", "0", "-1", "NULL", "NULL", "w657096904", "657096904", "way", "yes", "NULL", "NULL", "NULL", "NULL", "NULL", "NULL", "NULL", "NULL", "NULL", "NULL", "NULL", "NULL", "NULL", "NULL", "NULL", "NULL", "NULL", "NULL", "NULL", "NULL", "NULL", "NULL", "NULL", "NULL", "NULL", "NULL", "NULL", "NULL", "NULL", "NULL", "NULL", "NULL", "NULL", "NULL", "NULL", "NULL", "NULL", "NULL", "NULL", "NULL", "NULL", "NULL", "NULL", "NULL", "NULL", "NULL", "NULL", "NULL", "NULL", "NULL", "NULL", "NULL", "NULL", "NULL", "NULL", "NULL", "NULL", "NULL", "NULL", "NULL", "NULL", "NULL", "NULL", "NULL", "NULL", "NULL", "NULL", "NULL", "NULL", "NULL", "NULL", "NULL", "NULL", "NULL", "NULL", "NULL", "NULL", "NULL", "NULL", "NULL", "NULL", "NULL", "NULL", "NULL", "NULL", "NULL", "NULL", "NULL", "NULL", "NULL", "NULL", "NULL", "NULL", "NULL", "NULL", "NULL", "NULL", "NULL", "NULL", "NULL", "NULL", "NULL", "NULL", "NULL", "NULL", "NULL", "NULL", "NULL", "NULL", "NULL", "NULL", "NULL", "NULL", "NULL", "NULL", "NULL", "NULL", "NULL", "NULL", "NULL", "NULL", "NULL", "NULL", "NULL", "NULL", "NULL", "NULL", "NULL", "NULL", "NULL", "NULL", "NULL", "NULL", "NULL", "NULL", "NULL", "NULL", "NULL", "NULL", "NULL", "NULL", "NULL", "NULL", "NULL", "NULL", "NULL", "NULL", "NULL", "NULL", "NULL", "NULL", "NULL", "NULL", "NULL", "NULL", "NULL", "NULL", "NULL", "NULL", "NULL", "NULL", "NULL", "NULL", "NULL", "NULL", "NULL", "NULL", "NULL", "NULL", "0.02376475200283115", "0.21388276802548034", "9"]}, {"geom": {"polygons": [[[[-0.05075541393087235, -0.05652417796678044], [-0.050731513930870165, -0.05650197796678036], [-0.05059471393086312, -0.056637977966781605], [-0.05061861393086531, -0.05666017796678169], [-0.05075541393087235, -0.05652417796678044]]]], "centroids": [[-0.050675063930867736, -0.05658107796677925, 0.0]], "h": 8.14841856159415e-06}, "mtl": {"idx": 0}, "prop": ["72909", "building.72909", "NULL", "NULL", "NULL", "NULL", "NULL", "NULL", "-1", "0", "-1", "NULL", "NULL", "w657096906", "657096906", "way", "yes", "NULL", "NULL", "NULL", "NULL", "NULL", "NULL", "NULL", "NULL", "NULL", "NULL", "NULL", "NULL", "NULL", "NULL", "NULL", "NULL", "NULL", "NULL", "NULL", "NULL", "NULL", "NULL", "NULL", "NULL", "NULL", "NULL", "NULL", "NULL", "NULL", "NULL", "NULL", "NULL", "NULL", "NULL", "NULL", "NULL", "NULL", "NULL", "NULL", "NULL", "NULL", "NULL", "NULL", "NULL", "NULL", "NULL", "NULL", "NULL", "NULL", "NULL", "NULL", "NULL", "NULL", "NULL", "NULL", "NULL", "NULL", "NULL", "NULL", "NULL", "NULL", "NULL", "NULL", "NULL", "NULL", "NULL", "NULL", "NULL", "NULL", "NULL", "NULL", "NULL", "NULL", "NULL", "NULL", "NULL", "NULL", "NULL", "NULL", "NULL", "NULL", "NULL", "NULL", "NULL", "NULL", "NULL", "NULL", "NULL", "NULL", "NULL", "NULL", "NULL", "NULL", "NULL", "NULL", "NULL", "NULL", "NULL", "NULL", "NULL", "NULL", "NULL", "NULL", "NULL", "NULL", "NULL", "NULL", "NULL", "NULL", "NULL", "NULL", "NULL", "NULL", "NULL", "NULL", "NULL", "NULL", "NULL", "NULL", "NULL", "NULL", "NULL", "NULL", "NULL", "NULL", "NULL", "NULL", "NULL", "NULL", "NULL", "NULL", "NULL", "NULL", "NULL", "NULL", "NULL", "NULL", "NULL", "NULL", "NULL", "NULL", "NULL", "NULL", "NULL", "NULL", "NULL", "NULL", "NULL", "NULL", "NULL", "NULL", "NULL", "NULL", "NULL", "NULL", "NULL", "NULL", "NULL", "NULL", "NULL", "NULL", "NULL", "NULL", "NULL", "NULL", "NULL", "NULL", "NULL", "NULL", "0.08148418561594149", "0.7333576705434734", "9"]}, {"geom": {"polygons": [[[[-0.04708401393087058, -0.05535877796678079], [-0.047042813930872285, -0.05538437796678153], [-0.047081813930873295, -0.055442377966780754], [-0.04712301393087159, -0.055416677966780625], [-0.04708401393087058, -0.05535877796678079]]]], "centroids": [[-0.04708291349689375, -0.05540056112532454, 0.0]], "h": 4.390705439796497e-06}, "mtl": {"idx": 0}, "prop": ["18244", "building.18244", "NULL", "NULL", "NULL", "NULL", "NULL", "NULL", "-1", "0", "-1", "NULL", "NULL", "w596651327", "596651327", "way", "yes", "NULL", "NULL", "NULL", "NULL", "NULL", "NULL", "NULL", "NULL", "NULL", "NULL", "NULL", "NULL", "NULL", "NULL", "NULL", "NULL", "NULL", "NULL", "NULL", "NULL", "NULL", "NULL", "NULL", "NULL", "NULL", "NULL", "NULL", "NULL", "NULL", "NULL", "NULL", "NULL", "NULL", "NULL", "NULL", "NULL", "NULL", "NULL", "NULL", "NULL", "NULL", "NULL", "NULL", "NULL", "NULL", "NULL", "NULL", "NULL", "NULL", "NULL", "NULL", "NULL", "NULL", "NULL", "NULL", "NULL", "NULL", "NULL", "NULL", "NULL", "NULL", "NULL", "NULL", "NULL", "NULL", "NULL", "NULL", "NULL", "NULL", "NULL", "NULL", "NULL", "NULL", "NULL", "NULL", "NULL", "NULL", "NULL", "NULL", "NULL", "NULL", "NULL", "NULL", "NULL", "NULL", "NULL", "NULL", "NULL", "NULL", "NULL", "NULL", "NULL", "NULL", "NULL", "NULL", "NULL", "NULL", "NULL", "NULL", "NULL", "NULL", "NULL", "NULL", "NULL", "NULL", "NULL", "NULL", "NULL", "NULL", "NULL", "NULL", "NULL", "NULL", "NULL", "NULL", "NULL", "NULL", "NULL", "NULL", "NULL", "NULL", "NULL", "NULL", "NULL", "NULL", "NULL", "NULL", "NULL", "NULL", "NULL", "NULL", "NULL", "NULL", "NULL", "NULL", "NULL", "NULL", "NULL", "NULL", "NULL", "NULL", "NULL", "NULL", "NULL", "NULL", "NULL", "NULL", "NULL", "NULL", "NULL", "NULL", "NULL", "NULL", "NULL", "NULL", "NULL", "NULL", "NULL", "NULL", "NULL", "NULL", "NULL", "NULL", "NULL", "NULL", "NULL", "NULL", "NULL", "NULL", "0.043907054397964974", "0.287015162461691", "6.536880380547545"]}, {"geom": {"polygons": [[[[-0.04703701393086135, -0.055471477966781535], [-0.046974713930865164, -0.055377977966781344], [-0.04685591393086952, -0.05545117796678056], [-0.04690261393086814, -0.055543977966781455], [-0.04691831393085977, -0.05554467796678075], [-0.04703701393086135, -0.055471477966781535]]]], "centroids": [[-0.04694412468349185, -0.05546358491660719, 0.0]], "h": 2.1227546876296776e-05}, "mtl": {"idx": 0}, "prop": ["18242", "building.18242", "NULL", "NULL", "NULL", "NULL", "NULL", "NULL", "-1", "0", "-1", "NULL", "NULL", "w596651325", "596651325", "way", "yes", "NULL", "NULL", "NULL", "NULL", "NULL", "NULL", "NULL", "NULL", "NULL", "NULL", "NULL", "NULL", "NULL", "NULL", "NULL", "NULL", "NULL", "NULL", "NULL", "NULL", "NULL", "NULL", "NULL", "NULL", "NULL", "NULL", "NULL", "NULL", "NULL", "NULL", "NULL", "NULL", "NULL", "NULL", "NULL", "NULL", "NULL", "NULL", "NULL", "NULL", "NULL", "NULL", "NULL", "NULL", "NULL", "NULL", "NULL", "NULL", "NULL", "NULL", "NULL", "NULL", "NULL", "NULL", "NULL", "NULL", "NULL", "NULL", "NULL", "NULL", "NULL", "NULL", "NULL", "NULL", "NULL", "NULL", "NULL", "NULL", "NULL", "NULL", "NULL", "NULL", "NULL", "NULL", "NULL", "NULL", "NULL", "NULL", "NULL", "NULL", "NULL", "NULL", "NULL", "NULL", "NULL", "NULL", "NULL", "NULL", "NULL", "NULL", "NULL", "NULL", "NULL", "NULL", "NULL", "NULL", "NULL", "NULL", "NULL", "NULL", "NULL", "NULL", "NULL", "NULL", "NULL", "NULL", "NULL", "NULL", "NULL", "NULL", "NULL", "NULL", "NULL", "NULL", "NULL", "NULL", "NULL", "NULL", "NULL", "NULL", "NULL", "NULL", "NULL", "NULL", "NULL", "NULL", "NULL", "NULL", "NULL", "NULL", "NULL", "NULL", "NULL", "NULL", "NULL", "NULL", "NULL", "NULL", "NULL", "NULL", "NULL", "NULL", "NULL", "NULL", "NULL", "NULL", "NULL", "NULL", "NULL", "NULL", "NULL", "NULL", "NULL", "NULL", "NULL", "NULL", "NULL", "NULL", "NULL", "NULL", "NULL", "NULL", "NULL", "NULL", "NULL", "NULL", "NULL", "NULL", "NULL", "0.21227546876296774", "1.4797278650264079", "6.970790707232922"]}, {"geom": {"polygons": [[[[-0.04684821393087191, -0.055471377966780366], [-0.04671221393086, -0.055536777966780804], [-0.04678281393086081, -0.05564507796678164], [-0.04683781393086406, -0.05561777796678058], [-0.046830113930866446, -0.05559217796678162], [-0.04691191393087024, -0.05554997796678052], [-0.04684821393087191, -0.055471377966780366]]]], "centroids": [[-0.04680965824761074, -0.055553260311862473, 0.0]], "h": 2.257516656260786e-05}, "mtl": {"idx": 0}, "prop": ["18243", "building.18243", "NULL", "NULL", "NULL", "NULL", "NULL", "NULL", "-1", "0", "-1", "NULL", "NULL", "w596651326", "596651326", "way", "yes", "NULL", "NULL", "NULL", "NULL", "NULL", "NULL", "NULL", "NULL", "NULL", "NULL", "NULL", "NULL", "NULL", "NULL", "NULL", "NULL", "NULL", "NULL", "NULL", "NULL", "NULL", "NULL", "NULL", "NULL", "NULL", "NULL", "NULL", "NULL", "NULL", "NULL", "NULL", "NULL", "NULL", "NULL", "NULL", "NULL", "NULL", "NULL", "NULL", "NULL", "NULL", "NULL", "NULL", "NULL", "NULL", "NULL", "NULL", "NULL", "NULL", "NULL", "NULL", "NULL", "NULL", "NULL", "NULL", "NULL", "NULL", "NULL", "NULL", "NULL", "NULL", "NULL", "NULL", "NULL", "NULL", "NULL", "NULL", "NULL", "NULL", "NULL", "NULL", "NULL", "NULL", "NULL", "NULL", "NULL", "NULL", "NULL", "NULL", "NULL", "NULL", "NULL", "NULL", "NULL", "NULL", "NULL", "NULL", "NULL", "NULL", "NULL", "NULL", "NULL", "NULL", "NULL", "NULL", "NULL", "NULL", "NULL", "NULL", "NULL", "NULL", "NULL", "NULL", "NULL", "NULL", "NULL", "NULL", "NULL", "NULL", "NULL", "NULL", "NULL", "NULL", "NULL", "NULL", "NULL", "NULL", "NULL", "NULL", "NULL", "NULL", "NULL", "NULL", "NULL", "NULL", "NULL", "NULL", "NULL", "NULL", "NULL", "NULL", "NULL", "NULL", "NULL", "NULL", "NULL", "NULL", "NULL", "NULL", "NULL", "NULL", "NULL", "NULL", "NULL", "NULL", "NULL", "NULL", "NULL", "NULL", "NULL", "NULL", "NULL", "NULL", "NULL", "NULL", "NULL", "NULL", "NULL", "NULL", "NULL", "NULL", "NULL", "NULL", "NULL", "NULL", "NULL", "NULL", "NULL", "NULL", "0.2257516656260786", "1.5802616593825503", "7"]}, {"geom": {"polygons": [[[[-0.046778913930864974, -0.05566077796678037], [-0.04674441393086681, -0.05564267796678202], [-0.04671271393087295, -0.05569837796678101], [-0.04674721393087111, -0.055716577966780534], [-0.046778913930864974, -0.05566077796678037]]]], "centroids": [[-0.04674581454904114, -0.05567961094900298, 0.0]], "h": 3.238354079837525e-06}, "mtl": {"idx": 0}, "prop": ["18245", "building.18245", "NULL", "NULL", "NULL", "NULL", "NULL", "NULL", "-1", "0", "-1", "NULL", "NULL", "w596651330", "596651330", "way", "yes", "NULL", "NULL", "NULL", "NULL", "NULL", "NULL", "NULL", "NULL", "NULL", "NULL", "NULL", "NULL", "NULL", "NULL", "NULL", "NULL", "NULL", "NULL", "NULL", "NULL", "NULL", "NULL", "NULL", "NULL", "NULL", "NULL", "NULL", "NULL", "NULL", "NULL", "NULL", "NULL", "NULL", "NULL", "NULL", "NULL", "NULL", "NULL", "NULL", "NULL", "NULL", "NULL", "NULL", "NULL", "NULL", "NULL", "NULL", "NULL", "NULL", "NULL", "NULL", "NULL", "NULL", "NULL", "NULL", "NULL", "NULL", "NULL", "NULL", "NULL", "NULL", "NULL", "NULL", "NULL", "NULL", "NULL", "NULL", "NULL", "NULL", "NULL", "NULL", "NULL", "NULL", "NULL", "NULL", "NULL", "NULL", "NULL", "NULL", "NULL", "NULL", "NULL", "NULL", "NULL", "NULL", "NULL", "NULL", "NULL", "NULL", "NULL", "NULL", "NULL", "NULL", "NULL", "NULL", "NULL", "NULL", "NULL", "NULL", "NULL", "NULL", "NULL", "NULL", "NULL", "NULL", "NULL", "NULL", "NULL", "NULL", "NULL", "NULL", "NULL", "NULL", "NULL", "NULL", "NULL", "NULL", "NULL", "NULL", "NULL", "NULL", "NULL", "NULL", "NULL", "NULL", "NULL", "NULL", "NULL", "NULL", "NULL", "NULL", "NULL", "NULL", "NULL", "NULL", "NULL", "NULL", "NULL", "NULL", "NULL", "NULL", "NULL", "NULL", "NULL", "NULL", "NULL", "NULL", "NULL", "NULL", "NULL", "NULL", "NULL", "NULL", "NULL", "NULL", "NULL", "NULL", "NULL", "NULL", "NULL", "NULL", "NULL", "NULL", "NULL", "NULL", "NULL", "NULL", "NULL", "NULL", "0.03238354079837525", "0.24485764600496457", "7.5611758309409325"]}, {"geom": {"polygons": [[[[-0.046729513930870326, -0.05574667796678057], [-0.046695913930861366, -0.055727877966781136], [-0.04666531393087325, -0.05577817796678097], [-0.046698913930868, -0.05579707796678157], [-0.046729513930870326, -0.05574667796678057]]]], "centroids": [[-0.04669741463838761, -0.05576246095297854, 0.0]], "h": 2.9400667206107747e-06}, "mtl": {"idx": 0}, "prop": ["18246", "building.18246", "NULL", "NULL", "NULL", "NULL", "NULL", "NULL", "-1", "0", "-1", "NULL", "NULL", "w596651331", "596651331", "way", "yes", "NULL", "NULL", "NULL", "NULL", "NULL", "NULL", "NULL", "NULL", "NULL", "NULL", "NULL", "NULL", "NULL", "NULL", "NULL", "NULL", "NULL", "NULL", "NULL", "NULL", "NULL", "NULL", "NULL", "NULL", "NULL", "NULL", "NULL", "NULL", "NULL", "NULL", "NULL", "NULL", "NULL", "NULL", "NULL", "NULL", "NULL", "NULL", "NULL", "NULL", "NULL", "NULL", "NULL", "NULL", "NULL", "NULL", "NULL", "NULL", "NULL", "NULL", "NULL", "NULL", "NULL", "NULL", "NULL", "NULL", "NULL", "NULL", "NULL", "NULL", "NULL", "NULL", "NULL", "NULL", "NULL", "NULL", "NULL", "NULL", "NULL", "NULL", "NULL", "NULL", "NULL", "NULL", "NULL", "NULL", "NULL", "NULL", "NULL", "NULL", "NULL", "NULL", "NULL", "NULL", "NULL", "NULL", "NULL", "NULL", "NULL", "NULL", "NULL", "NULL", "NULL", "NULL", "NULL", "NULL", "NULL", "NULL", "NULL", "NULL", "NULL", "NULL", "NULL", "NULL", "NULL", "NULL", "NULL", "NULL", "NULL", "NULL", "NULL", "NULL", "NULL", "NULL", "NULL", "NULL", "NULL", "NULL", "NULL", "NULL", "NULL", "NULL", "NULL", "NULL", "NULL", "NULL", "NULL", "NULL", "NULL", "NULL", "NULL", "NULL", "NULL", "NULL", "NULL", "NULL", "NULL", "NULL", "NULL", "NULL", "NULL", "NULL", "NULL", "NULL", "NULL", "NULL", "NULL", "NULL", "NULL", "NULL", "NULL", "NULL", "NULL", "NULL", "NULL", "NULL", "NULL", "NULL", "NULL", "NULL", "NULL", "NULL", "NULL", "NULL", "NULL", "NULL", "NULL", "NULL", "NULL", "0.029400667206107747", "0.23520533764886198", "8"]}, {"geom": {"polygons": [[[[-0.04600521393086865, -0.05494087796678038], [-0.045975713930872075, -0.0549999779667818], [-0.04602391393086691, -0.055022277966781274], [-0.04605351393087176, -0.05496317796678163], [-0.04600521393086865, -0.05494087796678038]]]], "centroids": [[-0.04601459563068033, -0.05498157085600397, 0.0]], "h": 4.549659840243252e-06}, "mtl": {"idx": 0}, "prop": ["37310", "building.37310", "NULL", "NULL", "NULL", "NULL", "NULL", "NULL", "-1", "0", "-1", "NULL", "NULL", "w606240296", "606240296", "way", "yes", "NULL", "NULL", "NULL", "NULL", "NULL", "NULL", "NULL", "NULL", "NULL", "NULL", "NULL", "NULL", "NULL", "NULL", "NULL", "NULL", "NULL", "NULL", "NULL", "NULL", "NULL", "NULL", "NULL", "NULL", "NULL", "NULL", "NULL", "NULL", "NULL", "NULL", "NULL", "NULL", "NULL", "NULL", "NULL", "NULL", "NULL", "NULL", "NULL", "NULL", "NULL", "NULL", "NULL", "NULL", "NULL", "NULL", "NULL", "NULL", "NULL", "NULL", "NULL", "NULL", "NULL", "NULL", "NULL", "NULL", "NULL", "NULL", "NULL", "NULL", "NULL", "NULL", "NULL", "NULL", "NULL", "NULL", "NULL", "NULL", "NULL", "NULL", "NULL", "NULL", "NULL", "NULL", "NULL", "NULL", "NULL", "NULL", "NULL", "NULL", "NULL", "NULL", "NULL", "NULL", "NULL", "NULL", "NULL", "NULL", "NULL", "NULL", "NULL", "NULL", "NULL", "NULL", "NULL", "NULL", "NULL", "NULL", "NULL", "NULL", "NULL", "NULL", "NULL", "NULL", "NULL", "NULL", "NULL", "NULL", "NULL", "NULL", "NULL", "NULL", "NULL", "NULL", "NULL", "NULL", "NULL", "NULL", "NULL", "NULL", "NULL", "NULL", "NULL", "NULL", "NULL", "NULL", "NULL", "NULL", "NULL", "NULL", "NULL", "NULL", "NULL", "NULL", "NULL", "NULL", "NULL", "NULL", "NULL", "NULL", "NULL", "NULL", "NULL", "NULL", "NULL", "NULL", "NULL", "NULL", "NULL", "NULL", "NULL", "NULL", "NULL", "NULL", "NULL", "NULL", "NULL", "NULL", "NULL", "NULL", "NULL", "NULL", "NULL", "NULL", "NULL", "NULL", "NULL", "NULL", "NULL", "0.04549659840243251", "0.4094693856218926", "9"]}, {"geom": {"polygons": [[[[-0.04599121393086136, -0.055400977966781895], [-0.045894613930869355, -0.055479277966780316], [-0.045958513930870026, -0.055552077966781965], [-0.046007313930871874, -0.05551247796678105], [-0.04599221393087305, -0.055495277966780776], [-0.04604001393086321, -0.055456577966781495], [-0.04599121393086136, -0.055400977966781895]]]], "centroids": [[-0.0459683980383403, -0.055475462077909654, 0.0]], "h": 1.3772669759156343e-05}, "mtl": {"idx": 0}, "prop": ["18247", "building.18247", "NULL", "NULL", "NULL", "NULL", "NULL", "NULL", "-1", "0", "-1", "NULL", "NULL", "w596651332", "596651332", "way", "yes", "NULL", "NULL", "NULL", "NULL", "NULL", "NULL", "NULL", "NULL", "NULL", "NULL", "NULL", "NULL", "NULL", "NULL", "NULL", "NULL", "NULL", "NULL", "NULL", "NULL", "NULL", "NULL", "NULL", "NULL", "NULL", "NULL", "NULL", "NULL", "NULL", "NULL", "NULL", "NULL", "NULL", "NULL", "NULL", "NULL", "NULL", "NULL", "NULL", "NULL", "NULL", "NULL", "NULL", "NULL", "NULL", "NULL", "NULL", "NULL", "NULL", "NULL", "NULL", "NULL", "NULL", "NULL", "NULL", "NULL", "NULL", "NULL", "NULL", "NULL", "NULL", "NULL", "NULL", "NULL", "NULL", "NULL", "NULL", "NULL", "NULL", "NULL", "NULL", "NULL", "NULL", "NULL", "NULL", "NULL", "NULL", "NULL", "NULL", "NULL", "NULL", "NULL", "NULL", "NULL", "NULL", "NULL", "NULL", "NULL", "NULL", "NULL", "NULL", "NULL", "NULL", "NULL", "NULL", "NULL", "NULL", "NULL", "NULL", "NULL", "NULL", "NULL", "NULL", "NULL", "NULL", "NULL", "NULL", "NULL", "NULL", "NULL", "NULL", "NULL", "NULL", "NULL", "NULL", "NULL", "NULL", "NULL", "NULL", "NULL", "NULL", "NULL", "NULL", "NULL", "NULL", "NULL", "NULL", "NULL", "NULL", "NULL", "NULL", "NULL", "NULL", "NULL", "NULL", "NULL", "NULL", "NULL", "NULL", "NULL", "NULL", "NULL", "NULL", "NULL", "NULL", "NULL", "NULL", "NULL", "NULL", "NULL", "NULL", "NULL", "NULL", "NULL", "NULL", "NULL", "NULL", "NULL", "NULL", "NULL", "NULL", "NULL", "NULL", "NULL", "NULL", "NULL", "NULL", "NULL", "NULL", "0.13772669759156342", "1.1018135807325073", "8"]}, {"geom": {"polygons": [[[[-0.045919213930872615, -0.054927677966780664], [-0.04589621393085963, -0.05496477796678079], [-0.045958213930859415, -0.055000377966781144], [-0.04598131393086646, -0.05496317796678163], [-0.045919213930872615, -0.054927677966780664]]]], "centroids": [[-0.04593875594936492, -0.05496401082346303, 0.0]], "h": 4.049462160592459e-06}, "mtl": {"idx": 0}, "prop": ["37309", "building.37309", "NULL", "NULL", "NULL", "NULL", "NULL", "NULL", "-1", "0", "-1", "NULL", "NULL", "w606240295", "606240295", "way", "yes", "NULL", "NULL", "NULL", "NULL", "NULL", "NULL", "NULL", "NULL", "NULL", "NULL", "NULL", "NULL", "NULL", "NULL", "NULL", "NULL", "NULL", "NULL", "NULL", "NULL", "NULL", "NULL", "NULL", "NULL", "NULL", "NULL", "NULL", "NULL", "NULL", "NULL", "NULL", "NULL", "NULL", "NULL", "NULL", "NULL", "NULL", "NULL", "NULL", "NULL", "NULL", "NULL", "NULL", "NULL", "NULL", "NULL", "NULL", "NULL", "NULL", "NULL", "NULL", "NULL", "NULL", "NULL", "NULL", "NULL", "NULL", "NULL", "NULL", "NULL", "NULL", "NULL", "NULL", "NULL", "NULL", "NULL", "NULL", "NULL", "NULL", "NULL", "NULL", "NULL", "NULL", "NULL", "NULL", "NULL", "NULL", "NULL", "NULL", "NULL", "NULL", "NULL", "NULL", "NULL", "NULL", "NULL", "NULL", "NULL", "NULL", "NULL", "NULL", "NULL", "NULL", "NULL", "NULL", "NULL", "NULL", "NULL", "NULL", "NULL", "NULL", "NULL", "NULL", "NULL", "NULL", "NULL", "NULL", "NULL", "NULL", "NULL", "NULL", "NULL", "NULL", "NULL", "NULL", "NULL", "NULL", "NULL", "NULL", "NULL", "NULL", "NULL", "NULL", "NULL", "NULL", "NULL", "NULL", "NULL", "NULL", "NULL", "NULL", "NULL", "NULL", "NULL", "NULL", "NULL", "NULL", "NULL", "NULL", "NULL", "NULL", "NULL", "NULL", "NULL", "NULL", "NULL", "NULL", "NULL", "NULL", "NULL", "NULL", "NULL", "NULL", "NULL", "NULL", "NULL", "NULL", "NULL", "NULL", "NULL", "NULL", "NULL", "NULL", "NULL", "NULL", "NULL", "NULL", "NULL", "NULL", "0.04049462160592458", "0.36445159445332126", "9"]}, {"geom": {"polygons": [[[[-0.045912713930860605, -0.0549848779667812], [-0.04588011393086333, -0.05503637796678085], [-0.04592181393086037, -0.05506077796678177], [-0.04595441393087185, -0.055009277966780346], [-0.045912713930860605, -0.0549848779667812]]]], "centroids": [[-0.0459172639308747, -0.05502282796678237, 0.0]], "h": 3.814115040737621e-06}, "mtl": {"idx": 0}, "prop": ["37308", "building.37308", "NULL", "NULL", "NULL", "NULL", "NULL", "NULL", "-1", "0", "-1", "NULL", "NULL", "w606240294", "606240294", "way", "yes", "NULL", "NULL", "NULL", "NULL", "NULL", "NULL", "NULL", "NULL", "NULL", "NULL", "NULL", "NULL", "NULL", "NULL", "NULL", "NULL", "NULL", "NULL", "NULL", "NULL", "NULL", "NULL", "NULL", "NULL", "NULL", "NULL", "NULL", "NULL", "NULL", "NULL", "NULL", "NULL", "NULL", "NULL", "NULL", "NULL", "NULL", "NULL", "NULL", "NULL", "NULL", "NULL", "NULL", "NULL", "NULL", "NULL", "NULL", "NULL", "NULL", "NULL", "NULL", "NULL", "NULL", "NULL", "NULL", "NULL", "NULL", "NULL", "NULL", "NULL", "NULL", "NULL", "NULL", "NULL", "NULL", "NULL", "NULL", "NULL", "NULL", "NULL", "NULL", "NULL", "NULL", "NULL", "NULL", "NULL", "NULL", "NULL", "NULL", "NULL", "NULL", "NULL", "NULL", "NULL", "NULL", "NULL", "NULL", "NULL", "NULL", "NULL", "NULL", "NULL", "NULL", "NULL", "NULL", "NULL", "NULL", "NULL", "NULL", "NULL", "NULL", "NULL", "NULL", "NULL", "NULL", "NULL", "NULL", "NULL", "NULL", "NULL", "NULL", "NULL", "NULL", "NULL", "NULL", "NULL", "NULL", "NULL", "NULL", "NULL", "NULL", "NULL", "NULL", "NULL", "NULL", "NULL", "NULL", "NULL", "NULL", "NULL", "NULL", "NULL", "NULL", "NULL", "NULL", "NULL", "NULL", "NULL", "NULL", "NULL", "NULL", "NULL", "NULL", "NULL", "NULL", "NULL", "NULL", "NULL", "NULL", "NULL", "NULL", "NULL", "NULL", "NULL", "NULL", "NULL", "NULL", "NULL", "NULL", "NULL", "NULL", "NULL", "NULL", "NULL", "NULL", "NULL", "NULL", "NULL", "NULL", "0.03814115040737621", "0.34327035366638586", "9"]}, {"geom": {"polygons": [[[[-0.04588001393086927, -0.054963577966780974], [-0.04584301393086321, -0.055015277966781184], [-0.04586631393087259, -0.05503067796678174], [-0.04590331393086444, -0.05497887796678036], [-0.04588001393086927, -0.054963577966780974]]]], "centroids": [[-0.04587316004963782, -0.054997113643018736, 0.0]], "h": 2.298747600270541e-06}, "mtl": {"idx": 0}, "prop": ["37307", "building.37307", "NULL", "NULL", "NULL", "NULL", "NULL", "NULL", "-1", "0", "-1", "NULL", "NULL", "w606240293", "606240293", "way", "yes", "NULL", "NULL", "NULL", "NULL", "NULL", "NULL", "NULL", "NULL", "NULL", "NULL", "NULL", "NULL", "NULL", "NULL", "NULL", "NULL", "NULL", "NULL", "NULL", "NULL", "NULL", "NULL", "NULL", "NULL", "NULL", "NULL", "NULL", "NULL", "NULL", "NULL", "NULL", "NULL", "NULL", "NULL", "NULL", "NULL", "NULL", "NULL", "NULL", "NULL", "NULL", "NULL", "NULL", "NULL", "NULL", "NULL", "NULL", "NULL", "NULL", "NULL", "NULL", "NULL", "NULL", "NULL", "NULL", "NULL", "NULL", "NULL", "NULL", "NULL", "NULL", "NULL", "NULL", "NULL", "NULL", "NULL", "NULL", "NULL", "NULL", "NULL", "NULL", "NULL", "NULL", "NULL", "NULL", "NULL", "NULL", "NULL", "NULL", "NULL", "NULL", "NULL", "NULL", "NULL", "NULL", "NULL", "NULL", "NULL", "NULL", "NULL", "NULL", "NULL", "NULL", "NULL", "NULL", "NULL", "NULL", "NULL", "NULL", "NULL", "NULL", "NULL", "NULL", "NULL", "NULL", "NULL", "NULL", "NULL", "NULL", "NULL", "NULL", "NULL", "NULL", "NULL", "NULL", "NULL", "NULL", "NULL", "NULL", "NULL", "NULL", "NULL", "NULL", "NULL", "NULL", "NULL", "NULL", "NULL", "NULL", "NULL", "NULL", "NULL", "NULL", "NULL", "NULL", "NULL", "NULL", "NULL", "NULL", "NULL", "NULL", "NULL", "NULL", "NULL", "NULL", "NULL", "NULL", "NULL", "NULL", "NULL", "NULL", "NULL", "NULL", "NULL", "NULL", "NULL", "NULL", "NULL", "NULL", "NULL", "NULL", "NULL", "NULL", "NULL", "NULL", "NULL", "NULL", "NULL", "NULL", "0.02298747600270541", "0.20688728402434867", "9"]}, {"geom": {"polygons": [[[[-0.045826013930863496, -0.05514707796678131], [-0.04580181393086491, -0.05517327796678195], [-0.04583741393086882, -0.05520357796678077], [-0.04586151393087334, -0.055177377966781904], [-0.045826013930863496, -0.05514707796678131]]]], "centroids": [[-0.04583168036333518, -0.05517532680608639, 0.0]], "h": 2.155448880005718e-06}, "mtl": {"idx": 0}, "prop": ["37304", "building.37304", "NULL", "NULL", "NULL", "NULL", "NULL", "NULL", "-1", "0", "-1", "NULL", "NULL", "w606240290", "606240290", "way", "yes", "NULL", "NULL", "NULL", "NULL", "NULL", "NULL", "NULL", "NULL", "NULL", "NULL", "NULL", "NULL", "NULL", "NULL", "NULL", "NULL", "NULL", "NULL", "NULL", "NULL", "NULL", "NULL", "NULL", "NULL", "NULL", "NULL", "NULL", "NULL", "NULL", "NULL", "NULL", "NULL", "NULL", "NULL", "NULL", "NULL", "NULL", "NULL", "NULL", "NULL", "NULL", "NULL", "NULL", "NULL", "NULL", "NULL", "NULL", "NULL", "NULL", "NULL", "NULL", "NULL", "NULL", "NULL", "NULL", "NULL", "NULL", "NULL", "NULL", "NULL", "NULL", "NULL", "NULL", "NULL", "NULL", "NULL", "NULL", "NULL", "NULL", "NULL", "NULL", "NULL", "NULL", "NULL", "NULL", "NULL", "NULL", "NULL", "NULL", "NULL", "NULL", "NULL", "NULL", "NULL", "NULL", "NULL", "NULL", "NULL", "NULL", "NULL", "NULL", "NULL", "NULL", "NULL", "NULL", "NULL", "NULL", "NULL", "NULL", "NULL", "NULL", "NULL", "NULL", "NULL", "NULL", "NULL", "NULL", "NULL", "NULL", "NULL", "NULL", "NULL", "NULL", "NULL", "NULL", "NULL", "NULL", "NULL", "NULL", "NULL", "NULL", "NULL", "NULL", "NULL", "NULL", "NULL", "NULL", "NULL", "NULL", "NULL", "NULL", "NULL", "NULL", "NULL", "NULL", "NULL", "NULL", "NULL", "NULL", "NULL", "NULL", "NULL", "NULL", "NULL", "NULL", "NULL", "NULL", "NULL", "NULL", "NULL", "NULL", "NULL", "NULL", "NULL", "NULL", "NULL", "NULL", "NULL", "NULL", "NULL", "NULL", "NULL", "NULL", "NULL", "NULL", "NULL", "NULL", "NULL", "NULL", "0.021554488800057177", "0.19399039920051458", "9"]}, {"geom": {"polygons": [[[[-0.04579111393086066, -0.05517667796678083], [-0.04573551393086461, -0.05523067796678127], [-0.04576671393085974, -0.05526037796678196], [-0.045822313930869996, -0.05520627796678035], [-0.04579111393086066, -0.05517667796678083]]]], "centroids": [[-0.04577890863856737, -0.05521851278781398, 0.0]], "h": 4.32203039975899e-06}, "mtl": {"idx": 0}, "prop": ["37303", "building.37303", "NULL", "NULL", "NULL", "NULL", "NULL", "NULL", "-1", "0", "-1", "NULL", "NULL", "w606240289", "606240289", "way", "yes", "NULL", "NULL", "NULL", "NULL", "NULL", "NULL", "NULL", "NULL", "NULL", "NULL", "NULL", "NULL", "NULL", "NULL", "NULL", "NULL", "NULL", "NULL", "NULL", "NULL", "NULL", "NULL", "NULL", "NULL", "NULL", "NULL", "NULL", "NULL", "NULL", "NULL", "NULL", "NULL", "NULL", "NULL", "NULL", "NULL", "NULL", "NULL", "NULL", "NULL", "NULL", "NULL", "NULL", "NULL", "NULL", "NULL", "NULL", "NULL", "NULL", "NULL", "NULL", "NULL", "NULL", "NULL", "NULL", "NULL", "NULL", "NULL", "NULL", "NULL", "NULL", "NULL", "NULL", "NULL", "NULL", "NULL", "NULL", "NULL", "NULL", "NULL", "NULL", "NULL", "NULL", "NULL", "NULL", "NULL", "NULL", "NULL", "NULL", "NULL", "NULL", "NULL", "NULL", "NULL", "NULL", "NULL", "NULL", "NULL", "NULL", "NULL", "NULL", "NULL", "NULL", "NULL", "NULL", "NULL", "NULL", "NULL", "NULL", "NULL", "NULL", "NULL", "NULL", "NULL", "NULL", "NULL", "NULL", "NULL", "NULL", "NULL", "NULL", "NULL", "NULL", "NULL", "NULL", "NULL", "NULL", "NULL", "NULL", "NULL", "NULL", "NULL", "NULL", "NULL", "NULL", "NULL", "NULL", "NULL", "NULL", "NULL", "NULL", "NULL", "NULL", "NULL", "NULL", "NULL", "NULL", "NULL", "NULL", "NULL", "NULL", "NULL", "NULL", "NULL", "NULL", "NULL", "NULL", "NULL", "NULL", "NULL", "NULL", "NULL", "NULL", "NULL", "NULL", "NULL", "NULL", "NULL", "NULL", "NULL", "NULL", "NULL", "NULL", "NULL", "NULL", "NULL", "NULL", "NULL", "NULL", "0.0432203039975899", "0.42355307541689974", "9.799863403101432"]}, {"geom": {"polygons": [[[[-0.04574901393087316, -0.05512157796678174], [-0.045705013930870564, -0.05516597796678191], [-0.045744913930860776, -0.05520257796678152], [-0.04578891393086337, -0.055158277966780744], [-0.04574901393087316, -0.05512157796678174]]]], "centroids": [[-0.045746964778402344, -0.05516209455566212, 0.0]], "h": 4.38328583985425e-06}, "mtl": {"idx": 0}, "prop": ["37305", "building.37305", "NULL", "NULL", "NULL", "NULL", "NULL", "NULL", "-1", "0", "-1", "NULL", "NULL", "w606240291", "606240291", "way", "yes", "NULL", "NULL", "NULL", "NULL", "NULL", "NULL", "NULL", "NULL", "NULL", "NULL", "NULL", "NULL", "NULL", "NULL", "NULL", "NULL", "NULL", "NULL", "NULL", "NULL", "NULL", "NULL", "NULL", "NULL", "NULL", "NULL", "NULL", "NULL", "NULL", "NULL", "NULL", "NULL", "NULL", "NULL", "NULL", "NULL", "NULL", "NULL", "NULL", "NULL", "NULL", "NULL", "NULL", "NULL", "NULL", "NULL", "NULL", "NULL", "NULL", "NULL", "NULL", "NULL", "NULL", "NULL", "NULL", "NULL", "NULL", "NULL", "NULL", "NULL", "NULL", "NULL", "NULL", "NULL", "NULL", "NULL", "NULL", "NULL", "NULL", "NULL", "NULL", "NULL", "NULL", "NULL", "NULL", "NULL", "NULL", "NULL", "NULL", "NULL", "NULL", "NULL", "NULL", "NULL", "NULL", "NULL", "NULL", "NULL", "NULL", "NULL", "NULL", "NULL", "NULL", "NULL", "NULL", "NULL", "NULL", "NULL", "NULL", "NULL", "NULL", "NULL", "NULL", "NULL", "NULL", "NULL", "NULL", "NULL", "NULL", "NULL", "NULL", "NULL", "NULL", "NULL", "NULL", "NULL", "NULL", "NULL", "NULL", "NULL", "NULL", "NULL", "NULL", "NULL", "NULL", "NULL", "NULL", "NULL", "NULL", "NULL", "NULL", "NULL", "NULL", "NULL", "NULL", "NULL", "NULL", "NULL", "NULL", "NULL", "NULL", "NULL", "NULL", "NULL", "NULL", "NULL", "NULL", "NULL", "NULL", "NULL", "NULL", "NULL", "NULL", "NULL", "NULL", "NULL", "NULL", "NULL", "NULL", "NULL", "NULL", "NULL", "NULL", "NULL", "NULL", "NULL", "NULL", "NULL", "NULL", "0.04383285839854249", "0.43832858398542496", "10"]}, {"geom": {"polygons": [[[[-0.0457309139308677, -0.05506747796678191], [-0.0456674139308717, -0.05512927796678113], [-0.04569681393086, -0.055157177966780324], [-0.04576031393087021, -0.05509547796678049], [-0.0457309139308677, -0.05506747796678191]]]], "centroids": [[-0.04571387128380877, -0.05511234195821224, 0.0]], "h": 4.652996399841553e-06}, "mtl": {"idx": 0}, "prop": ["37306", "building.37306", "NULL", "NULL", "NULL", "NULL", "NULL", "NULL", "-1", "0", "-1", "NULL", "NULL", "w606240292", "606240292", "way", "yes", "NULL", "NULL", "NULL", "NULL", "NULL", "NULL", "NULL", "NULL", "NULL", "NULL", "NULL", "NULL", "NULL", "NULL", "NULL", "NULL", "NULL", "NULL", "NULL", "NULL", "NULL", "NULL", "NULL", "NULL", "NULL", "NULL", "NULL", "NULL", "NULL", "NULL", "NULL", "NULL", "NULL", "NULL", "NULL", "NULL", "NULL", "NULL", "NULL", "NULL", "NULL", "NULL", "NULL", "NULL", "NULL", "NULL", "NULL", "NULL", "NULL", "NULL", "NULL", "NULL", "NULL", "NULL", "NULL", "NULL", "NULL", "NULL", "NULL", "NULL", "NULL", "NULL", "NULL", "NULL", "NULL", "NULL", "NULL", "NULL", "NULL", "NULL", "NULL", "NULL", "NULL", "NULL", "NULL", "NULL", "NULL", "NULL", "NULL", "NULL", "NULL", "NULL", "NULL", "NULL", "NULL", "NULL", "NULL", "NULL", "NULL", "NULL", "NULL", "NULL", "NULL", "NULL", "NULL", "NULL", "NULL", "NULL", "NULL", "NULL", "NULL", "NULL", "NULL", "NULL", "NULL", "NULL", "NULL", "NULL", "NULL", "NULL", "NULL", "NULL", "NULL", "NULL", "NULL", "NULL", "NULL", "NULL", "NULL", "NULL", "NULL", "NULL", "NULL", "NULL", "NULL", "NULL", "NULL", "NULL", "NULL", "NULL", "NULL", "NULL", "NULL", "NULL", "NULL", "NULL", "NULL", "NULL", "NULL", "NULL", "NULL", "NULL", "NULL", "NULL", "NULL", "NULL", "NULL", "NULL", "NULL", "NULL", "NULL", "NULL", "NULL", "NULL", "NULL", "NULL", "NULL", "NULL", "NULL", "NULL", "NULL", "NULL", "NULL", "NULL", "NULL", "NULL", "NULL", "NULL", "NULL", "0.046529963998415524", "0.4652996399841552", "9.999999999999998"]}, {"geom": {"polygons": [[[[-0.04574301393085989, -0.055853177966781686], [-0.04565681393086152, -0.055893577966781294], [-0.04568261393086459, -0.05594447796678104], [-0.04576881393086296, -0.05590407796678143], [-0.04574301393085989, -0.055853177966781686]]]], "centroids": [[-0.04571281393086224, -0.05589882796678047, 0.0]], "h": 7.037150400150187e-06}, "mtl": {"idx": 0}, "prop": ["18250", "building.18250", "NULL", "NULL", "NULL", "NULL", "NULL", "NULL", "-1", "0", "-1", "NULL", "NULL", "w596651338", "596651338", "way", "yes", "NULL", "NULL", "NULL", "NULL", "NULL", "NULL", "NULL", "NULL", "NULL", "NULL", "NULL", "NULL", "NULL", "NULL", "NULL", "NULL", "NULL", "NULL", "NULL", "NULL", "NULL", "NULL", "NULL", "NULL", "NULL", "NULL", "NULL", "NULL", "NULL", "NULL", "NULL", "NULL", "NULL", "NULL", "NULL", "NULL", "NULL", "NULL", "NULL", "NULL", "NULL", "NULL", "NULL", "NULL", "NULL", "NULL", "NULL", "NULL", "NULL", "NULL", "NULL", "NULL", "NULL", "NULL", "NULL", "NULL", "NULL", "NULL", "NULL", "NULL", "NULL", "NULL", "NULL", "NULL", "NULL", "NULL", "NULL", "NULL", "NULL", "NULL", "NULL", "NULL", "NULL", "NULL", "NULL", "NULL", "NULL", "NULL", "NULL", "NULL", "NULL", "NULL", "NULL", "NULL", "NULL", "NULL", "NULL", "NULL", "NULL", "NULL", "NULL", "NULL", "NULL", "NULL", "NULL", "NULL", "NULL", "NULL", "NULL", "NULL", "NULL", "NULL", "NULL", "NULL", "NULL", "NULL", "NULL", "NULL", "NULL", "NULL", "NULL", "NULL", "NULL", "NULL", "NULL", "NULL", "NULL", "NULL", "NULL", "NULL", "NULL", "NULL", "NULL", "NULL", "NULL", "NULL", "NULL", "NULL", "NULL", "NULL", "NULL", "NULL", "NULL", "NULL", "NULL", "NULL", "NULL", "NULL", "NULL", "NULL", "NULL", "NULL", "NULL", "NULL", "NULL", "NULL", "NULL", "NULL", "NULL", "NULL", "NULL", "NULL", "NULL", "NULL", "NULL", "NULL", "NULL", "NULL", "NULL", "NULL", "NULL", "NULL", "NULL", "NULL", "NULL", "NULL", "NULL", "NULL", "NULL", "0.07037150400150187", "0.562972032012015", "8"]}, {"geom": {"polygons": [[[[-0.04572941393087149, -0.05523637796678038], [-0.04570291393086734, -0.055265577966780555], [-0.04573481393086354, -0.055292477966780496], [-0.04576141393086175, -0.05526327796678032], [-0.04572941393087149, -0.05523637796678038]]]], "centroids": [[-0.045732147201363205, -0.05526442731398262, 0.0]], "h": 2.1346869597289717e-06}, "mtl": {"idx": 0}, "prop": ["37302", "building.37302", "NULL", "NULL", "NULL", "NULL", "NULL", "NULL", "-1", "0", "-1", "NULL", "NULL", "w606240288", "606240288", "way", "yes", "NULL", "NULL", "NULL", "NULL", "NULL", "NULL", "NULL", "NULL", "NULL", "NULL", "NULL", "NULL", "NULL", "NULL", "NULL", "NULL", "NULL", "NULL", "NULL", "NULL", "NULL", "NULL", "NULL", "NULL", "NULL", "NULL", "NULL", "NULL", "NULL", "NULL", "NULL", "NULL", "NULL", "NULL", "NULL", "NULL", "NULL", "NULL", "NULL", "NULL", "NULL", "NULL", "NULL", "NULL", "NULL", "NULL", "NULL", "NULL", "NULL", "NULL", "NULL", "NULL", "NULL", "NULL", "NULL", "NULL", "NULL", "NULL", "NULL", "NULL", "NULL", "NULL", "NULL", "NULL", "NULL", "NULL", "NULL", "NULL", "NULL", "NULL", "NULL", "NULL", "NULL", "NULL", "NULL", "NULL", "NULL", "NULL", "NULL", "NULL", "NULL", "NULL", "NULL", "NULL", "NULL", "NULL", "NULL", "NULL", "NULL", "NULL", "NULL", "NULL", "NULL", "NULL", "NULL", "NULL", "NULL", "NULL", "NULL", "NULL", "NULL", "NULL", "NULL", "NULL", "NULL", "NULL", "NULL", "NULL", "NULL", "NULL", "NULL", "NULL", "NULL", "NULL", "NULL", "NULL", "NULL", "NULL", "NULL", "NULL", "NULL", "NULL", "NULL", "NULL", "NULL", "NULL", "NULL", "NULL", "NULL", "NULL", "NULL", "NULL", "NULL", "NULL", "NULL", "NULL", "NULL", "NULL", "NULL", "NULL", "NULL", "NULL", "NULL", "NULL", "NULL", "NULL", "NULL", "NULL", "NULL", "NULL", "NULL", "NULL", "NULL", "NULL", "NULL", "NULL", "NULL", "NULL", "NULL", "NULL", "NULL", "NULL", "NULL", "NULL", "NULL", "NULL", "NULL", "NULL", "NULL", "0.021346869597289715", "0.21346869597289714", "10"]}, {"geom": {"polygons": [[[[-0.04570691393087145, -0.05518477796678134], [-0.04568701393087338, -0.05521047796678147], [-0.045717513930867426, -0.05523217796678104], [-0.04573731393087144, -0.05520647796678091], [-0.04570691393087145, -0.05518477796678134]]]], "centroids": [[-0.04571218088875639, -0.05520847926900174, 0.0]], "h": 1.5724497602755083e-06}, "mtl": {"idx": 0}, "prop": ["37296", "building.37296", "NULL", "NULL", "NULL", "NULL", "NULL", "NULL", "-1", "0", "-1", "NULL", "NULL", "w606240282", "606240282", "way", "yes", "NULL", "NULL", "NULL", "NULL", "NULL", "NULL", "NULL", "NULL", "NULL", "NULL", "NULL", "NULL", "NULL", "NULL", "NULL", "NULL", "NULL", "NULL", "NULL", "NULL", "NULL", "NULL", "NULL", "NULL", "NULL", "NULL", "NULL", "NULL", "NULL", "NULL", "NULL", "NULL", "NULL", "NULL", "NULL", "NULL", "NULL", "NULL", "NULL", "NULL", "NULL", "NULL", "NULL", "NULL", "NULL", "NULL", "NULL", "NULL", "NULL", "NULL", "NULL", "NULL", "NULL", "NULL", "NULL", "NULL", "NULL", "NULL", "NULL", "NULL", "NULL", "NULL", "NULL", "NULL", "NULL", "NULL", "NULL", "NULL", "NULL", "NULL", "NULL", "NULL", "NULL", "NULL", "NULL", "NULL", "NULL", "NULL", "NULL", "NULL", "NULL", "NULL", "NULL", "NULL", "NULL", "NULL", "NULL", "NULL", "NULL", "NULL", "NULL", "NULL", "NULL", "NULL", "NULL", "NULL", "NULL", "NULL", "NULL", "NULL", "NULL", "NULL", "NULL", "NULL", "NULL", "NULL", "NULL", "NULL", "NULL", "NULL", "NULL", "NULL", "NULL", "NULL", "NULL", "NULL", "NULL", "NULL", "NULL", "NULL", "NULL", "NULL", "NULL", "NULL", "NULL", "NULL", "NULL", "NULL", "NULL", "NULL", "NULL", "NULL", "NULL", "NULL", "NULL", "NULL", "NULL", "NULL", "NULL", "NULL", "NULL", "NULL", "NULL", "NULL", "NULL", "NULL", "NULL", "NULL", "NULL", "NULL", "NULL", "NULL", "NULL", "NULL", "NULL", "NULL", "NULL", "NULL", "NULL", "NULL", "NULL", "NULL", "NULL", "NULL", "NULL", "NULL", "NULL", "NULL", "NULL", "0.015724497602755082", "0.15724497602755083", "10"]}, {"geom": {"polygons": [[[[-0.04569351393087118, -0.055164177966780414], [-0.04568341393085973, -0.055177277966780736], [-0.04569531393086379, -0.05518577796678059], [-0.04570541393086103, -0.05517267796678027], [-0.04569351393087118, -0.055164177966780414]]]], "centroids": [[-0.04569441393087459, -0.05517497796677873, 0.0]], "h": 3.132950401138335e-07}, "mtl": {"idx": 0}, "prop": ["37293", "building.37293", "NULL", "NULL", "NULL", "NULL", "NULL", "NULL", "-1", "0", "-1", "NULL", "NULL", "w606240279", "606240279", "way", "yes", "NULL", "NULL", "NULL", "NULL", "NULL", "NULL", "NULL", "NULL", "NULL", "NULL", "NULL", "NULL", "NULL", "NULL", "NULL", "NULL", "NULL", "NULL", "NULL", "NULL", "NULL", "NULL", "NULL", "NULL", "NULL", "NULL", "NULL", "NULL", "NULL", "NULL", "NULL", "NULL", "NULL", "NULL", "NULL", "NULL", "NULL", "NULL", "NULL", "NULL", "NULL", "NULL", "NULL", "NULL", "NULL", "NULL", "NULL", "NULL", "NULL", "NULL", "NULL", "NULL", "NULL", "NULL", "NULL", "NULL", "NULL", "NULL", "NULL", "NULL", "NULL", "NULL", "NULL", "NULL", "NULL", "NULL", "NULL", "NULL", "NULL", "NULL", "NULL", "NULL", "NULL", "NULL", "NULL", "NULL", "NULL", "NULL", "NULL", "NULL", "NULL", "NULL", "NULL", "NULL", "NULL", "NULL", "NULL", "NULL", "NULL", "NULL", "NULL", "NULL", "NULL", "NULL", "NULL", "NULL", "NULL", "NULL", "NULL", "NULL", "NULL", "NULL", "NULL", "NULL", "NULL", "NULL", "NULL", "NULL", "NULL", "NULL", "NULL", "NULL", "NULL", "NULL", "NULL", "NULL", "NULL", "NULL", "NULL", "NULL", "NULL", "NULL", "NULL", "NULL", "NULL", "NULL", "NULL", "NULL", "NULL", "NULL", "NULL", "NULL", "NULL", "NULL", "NULL", "NULL", "NULL", "NULL", "NULL", "NULL", "NULL", "NULL", "NULL", "NULL", "NULL", "NULL", "NULL", "NULL", "NULL", "NULL", "NULL", "NULL", "NULL", "NULL", "NULL", "NULL", "NULL", "NULL", "NULL", "NULL", "NULL", "NULL", "NULL", "NULL", "NULL", "NULL", "NULL", "NULL", "NULL", "0.0031329504011383346", "0.03132950401138335", "10"]}, {"geom": {"polygons": [[[[-0.045688113930864915, -0.05526917796678177], [-0.045667713930868103, -0.055295377966780634], [-0.04568231393086819, -0.05530577796678138], [-0.04570261393087094, -0.055279577966780735], [-0.045688113930864915, -0.05526917796678177]]]], "centroids": [[-0.04568517930940175, -0.0552874860953132, 0.0]], "h": 7.683336002738849e-07}, "mtl": {"idx": 0}, "prop": ["37295", "building.37295", "NULL", "NULL", "NULL", "NULL", "NULL", "NULL", "-1", "0", "-1", "NULL", "NULL", "w606240281", "606240281", "way", "yes", "NULL", "NULL", "NULL", "NULL", "NULL", "NULL", "NULL", "NULL", "NULL", "NULL", "NULL", "NULL", "NULL", "NULL", "NULL", "NULL", "NULL", "NULL", "NULL", "NULL", "NULL", "NULL", "NULL", "NULL", "NULL", "NULL", "NULL", "NULL", "NULL", "NULL", "NULL", "NULL", "NULL", "NULL", "NULL", "NULL", "NULL", "NULL", "NULL", "NULL", "NULL", "NULL", "NULL", "NULL", "NULL", "NULL", "NULL", "NULL", "NULL", "NULL", "NULL", "NULL", "NULL", "NULL", "NULL", "NULL", "NULL", "NULL", "NULL", "NULL", "NULL", "NULL", "NULL", "NULL", "NULL", "NULL", "NULL", "NULL", "NULL", "NULL", "NULL", "NULL", "NULL", "NULL", "NULL", "NULL", "NULL", "NULL", "NULL", "NULL", "NULL", "NULL", "NULL", "NULL", "NULL", "NULL", "NULL", "NULL", "NULL", "NULL", "NULL", "NULL", "NULL", "NULL", "NULL", "NULL", "NULL", "NULL", "NULL", "NULL", "NULL", "NULL", "NULL", "NULL", "NULL", "NULL", "NULL", "NULL", "NULL", "NULL", "NULL", "NULL", "NULL", "NULL", "NULL", "NULL", "NULL", "NULL", "NULL", "NULL", "NULL", "NULL", "NULL", "NULL", "NULL", "NULL", "NULL", "NULL", "NULL", "NULL", "NULL", "NULL", "NULL", "NULL", "NULL", "NULL", "NULL", "NULL", "NULL", "NULL", "NULL", "NULL", "NULL", "NULL", "NULL", "NULL", "NULL", "NULL", "NULL", "NULL", "NULL", "NULL", "NULL", "NULL", "NULL", "NULL", "NULL", "NULL", "NULL", "NULL", "NULL", "NULL", "NULL", "NULL", "NULL", "NULL", "NULL", "NULL", "NULL", "0.007683336002738848", "0.07683336002738848", "10"]}, {"geom": {"polygons": [[[[-0.04565101393086479, -0.055095777966780446], [-0.04563291393085933, -0.05511917796678034], [-0.04565431393086783, -0.0551344779667815], [-0.04567241393087329, -0.05511107796678161], [-0.04565101393086479, -0.055095777966780446]]]], "centroids": [[-0.04565266393086631, -0.055115127966780975, 0.0]], "h": 1.0078862402327579e-06}, "mtl": {"idx": 0}, "prop": ["37294", "building.37294", "NULL", "NULL", "NULL", "NULL", "NULL", "NULL", "-1", "0", "-1", "NULL", "NULL", "w606240280", "606240280", "way", "yes", "NULL", "NULL", "NULL", "NULL", "NULL", "NULL", "NULL", "NULL", "NULL", "NULL", "NULL", "NULL", "NULL", "NULL", "NULL", "NULL", "NULL", "NULL", "NULL", "NULL", "NULL", "NULL", "NULL", "NULL", "NULL", "NULL", "NULL", "NULL", "NULL", "NULL", "NULL", "NULL", "NULL", "NULL", "NULL", "NULL", "NULL", "NULL", "NULL", "NULL", "NULL", "NULL", "NULL", "NULL", "NULL", "NULL", "NULL", "NULL", "NULL", "NULL", "NULL", "NULL", "NULL", "NULL", "NULL", "NULL", "NULL", "NULL", "NULL", "NULL", "NULL", "NULL", "NULL", "NULL", "NULL", "NULL", "NULL", "NULL", "NULL", "NULL", "NULL", "NULL", "NULL", "NULL", "NULL", "NULL", "NULL", "NULL", "NULL", "NULL", "NULL", "NULL", "NULL", "NULL", "NULL", "NULL", "NULL", "NULL", "NULL", "NULL", "NULL", "NULL", "NULL", "NULL", "NULL", "NULL", "NULL", "NULL", "NULL", "NULL", "NULL", "NULL", "NULL", "NULL", "NULL", "NULL", "NULL", "NULL", "NULL", "NULL", "NULL", "NULL", "NULL", "NULL", "NULL", "NULL", "NULL", "NULL", "NULL", "NULL", "NULL", "NULL", "NULL", "NULL", "NULL", "NULL", "NULL", "NULL", "NULL", "NULL", "NULL", "NULL", "NULL", "NULL", "NULL", "NULL", "NULL", "NULL", "NULL", "NULL", "NULL", "NULL", "NULL", "NULL", "NULL", "NULL", "NULL", "NULL", "NULL", "NULL", "NULL", "NULL", "NULL", "NULL", "NULL", "NULL", "NULL", "NULL", "NULL", "NULL", "NULL", "NULL", "NULL", "NULL", "NULL", "NULL", "NULL", "NULL", "NULL", "0.010078862402327578", "0.10078862402327576", "9.999999999999998"]}], "featureCount": 50, "startIndex": 26050}